Workbook

Sheet Leads B2B
A1: NetWiz Systems | Base de dados de prospeção P1 - Leads B2B (Portugal e Espanha)
A2: 166 entidades (80 Portugal + 86 Espanha) em 8 setores prioritários da A4; inclui a base A3 - fontes públicas; nomes oficiais confirmados via web (jul/2026)
A3: Como ler: 4 folhas -> Leads B2B (esta) · Análise (conclusões) · Metodologia (critérios e RGPD) · Glossário (siglas). Prioridade (cor na coluna L): Alta = abordar primeiro · Média = seguir · Baixa = oportunista. Colunas J-K (necessidade/motivo): sinais públicos verificados + inferências de processos internos a validar; a Prioridade (L) é uma recomendação. O serviço NetWiz adequado é atribuído na Tarefa P2 (scorecard).
A4: N.º | B4: País | C4: Empresa / Entidade | D4: Cidade | E4: Setor | F4: Dimensão | G4: Website | H4: Email | I4: Contacto público | J4: Redes sociais | K4: Oportunidade identificada (necessidade digital) | L4: Motivo de interesse | M4: Prioridade | N4: Origem / Estado do dado | O4: Observações
A5: 1 | B5: Portugal | C5: EPET - Escola Profissional de Estudos Técnicos | D5: Lisboa | E5: Educação, ensino profissional e formação | F5: Média | G5: epet.pt | H5: epet@epet.pt | I5: +351 217 609 287 | J5: LinkedIn: https://www.linkedin.com/company/epet---escola-profissional-de-estudos-técnicos/ · Presença institucional pouca ativa | K5: Já tem Moodle, portal do aluno e inscrição online; lacunas menores de otimização e comunicação. | L5: Escola do Grupo Ensinus, digitalmente madura; oportunidade sobretudo de SEO, conversão e comunicação, não de raiz. | M5: Média | N5: Confirmado - verificação web (Exa, jul/2026) | O5: Justificação confirmada e atualizada ao site real.
A6: 2 | B6: Portugal | C6: Escola do Saber | D6: Leiria | E6: Educação, ensino profissional e formação | F6: Pequena | G6: escoladosaber.pt | H6: apoio@escoladosaber.pt | I6: +351 244 097 542 | J6: LinkedIn: https://www.linkedin.com/company/escola-do-saber---formação-profissional/ | K6: Site claramente desatualizado, sem área de formandos nem qualquer componente interativa. | L6: Pequena escola cuja imagem online não reflete a oferta formativa; um redesenho e um portal do formador teriam impacto imediato. | M6: Alta | N6: Confirmado - verificação web (Exa, jul/2026) | O6: Verificado: descrição confere com o site.
A7: 3 | B7: Portugal | C7: EPDRG - Escola Profissional de Desenvolvimento Rural de Grândola | D7: Grândola | E7: Educação, ensino profissional e formação | F7: Pequena | G7: epdrgrandola.pt | H7: direpdrg@gmail.com | I7: +351 269 441 222 | J7: Sem pagina de empresa no LinkedIn | K7: Site atual (notícias 2026) e oferta formativa estruturada; falta portal do aluno/área reservada. | L7: Presença web razoável; oportunidade num portal do aluno e na automatização de candidaturas. | M7: Média | N7: Confirmado - verificação web (Exa, jul/2026) | O7: Nome oficial: Nome oficial no site é "...de Desenvolvimento Rural de Grândola". | Justificação confirmada e atualizada ao site real.
A8: 4 | B8: Portugal | C8: FEPS - Fundação Escola Profissional de Setúbal | D8: Setúbal | E8: Educação, ensino profissional e formação | F8: Média | G8: eps.pt | H8: secretaria@eps.pt | I8: +351 265 729 900 | J8: LinkedIn: https://www.linkedin.com/company/escolaprofissionaldesetubal/ · Redes pouco dinamizadas | K8: O site e básico e sem interatividade, não havendo portal de aluno nem área de parceiros. | L8: Fundação com dimensao para justificar portais dedicados a alunos e a empresas parceiras. | M8: Alta | N8: Confirmado - verificação web (Exa, jul/2026) | O8: Verificado: descrição confere com o site. LinkedIn de empresa confirmado por pesquisa (Exa, jul/2026).
A9: 5 | B9: Portugal | C9: CENFIC / CICCOPN - Academia Lisboa | D9: Loures | E9: Educação, ensino profissional e formação | F9: Grande | G9: cenfic.pt | H9: cenfic@cenfic.pt | I9: +351 219 406 300 | J9: LinkedIn: https://www.linkedin.com/company/cenficcfp/ · Presença digital dispersa | K9: Já tem plataforma de e-learning (LMS) própria e marcações online; lacunas de UX e comunicação. | L9: Centro com LMS ativo; oportunidade de redesenho de UX/UI e reforço de comunicação, não de LMS de raiz. | M9: Média | N9: Confirmado - verificação web (Exa, jul/2026) | O9: Nome oficial: O domínio remete agora para CICCOPN - Academia Lisboa (tem LMS próprio). | Justificação confirmada e atualizada ao site real.
A10: 6 | B10: Portugal | C10: CEAC Corporate - Formação Online | D10: Lisboa | E10: Educação, ensino profissional e formação | F10: Média | G10: ceac-corporate.pt | H10: info@ceac.pt | I10: Formulario no site | J10: Comunicação pouco segmentada | K10: Interface antiquada e percursos de conversao demasiado longos para quem procura formação online. | L10: Opera em ensino a distância, onde a taxa de conversao do site e critica; há ganho claro em rebranding e otimização de campanhas. | M10: Média | N10: Confirmado - verificação web (Exa, jul/2026) | O10: Nome oficial: Marca oficial no site: CEAC Corporate.
A11: 7 | B11: Portugal | C11: Escola Profissional de Torres Vedras | D11: Torres Vedras | E11: Educação, ensino profissional e formação | F11: Pequena | G11: Via CM Torres Vedras | H11: geral@eptv.pt | I11: Site municipal | J11: Sem canais próprios | K11: Depende inteiramente do portal da autarquia, sem domínio nem site próprio. | L11: Escola sem identidade digital autonoma; comeca praticamente do zero, o que a torna uma oportunidade completa. | M11: Média | N11: Validado por análise - fonte pública (justificação estrutural), jul/2026
A12: 8 | B12: Portugal | C12: Escola Profissional de Braga (EPB) | D12: Braga | E12: Educação, ensino profissional e formação | F12: Média | G12: epb.pt | H12: epb@epb.pt | I12: +351 253 254 540 | J12: LinkedIn: https://www.linkedin.com/company/epb-escola-profissional-de-braga/ · Redes com pouca atividade | K12: Escola digitalmente avançada (Microsoft Showcase School); pré-inscrição online, portal de ex-alunos e bolsa de emprego. | L12: Maturidade digital alta; oportunidade pontual de otimização e comunicação. | M12: Baixa | N12: Confirmado - verificação web (Exa, jul/2026) | O12: Justificação confirmada e atualizada ao site real.
A13: 9 | B13: Portugal | C13: Insignare - EPO Escola Profissional de Ourém | D13: Ourém | E13: Educação, ensino profissional e formação | F13: Pequena | G13: insignare.pt | H13: epo@insignare.pt | I13: +351 249 540 390 | J13: LinkedIn: https://www.linkedin.com/company/insignare---associação-de-ensino-e-formação/ | K13: Site com baixa frequência de atualização e ausência de presença profissional nas redes. | L13: Escola local que ganharia visibilidade junto de empregadores com um LinkedIn ativo e captação de leads mais organizada. | M13: Média | N13: Confirmado - verificação web (Exa, jul/2026) | O13: Contacto corrigido (o anterior era inválido). insignare.pt gere a EPO e a Escola de Hotelaria de Fátima.
A14: 10 | B14: Portugal | C14: EPRAL - Escola Profissional da Região Alentejo | D14: Portalegre | E14: Educação, ensino profissional e formação | F14: Pequena | G14: epral.pt | H14: geral@epral.pt | I14: +351 245 339 190 | J14: LinkedIn: https://www.linkedin.com/company/escola-profissional-da-região-alentejo/ · Redes pouco presentes | K14: Site atual (2026) com oferta formativa estruturada; falta portal de candidatura/área do aluno. | L14: Presença web atual; oportunidade num portal de candidatura e área reservada. | M14: Média | N14: Confirmado - verificação web (Exa, jul/2026) | O14: Nome oficial: EPRAL = Escola Profissional da Região Alentejo (não "de Portalegre"). | Justificação confirmada e atualizada ao site real. LinkedIn de empresa confirmado por pesquisa (Exa, jul/2026).
A15: 11 | B15: Portugal | C15: Escola Profissional Bento de Jesus Caraca | D15: Lisboa | E15: Educação, ensino profissional e formação | F15: Grande | G15: epbjc.pt | H15: geral@epbjc.pt | I15: +351 211 945 915 | J15: LinkedIn: https://www.linkedin.com/school/escola-profissional-bento-de-jesus-caraça/ · Presença fragmentada por polos | K15: Navegação complexa entre varios polos e formulários que não entram em nenhum CRM. | L15: Rede multipolo com muitos candidatos; a gestão centralizada de leads e o encaminhamento por curso fariam grande diferenca. | M15: Alta | N15: Confirmado - verificação web (Exa, jul/2026) | O15: Verificado: Site ativo; multi-polo; sem portal de aluno visível - coerente.
A16: 12 | B16: Portugal | C16: Escola Profissional de Salvaterra de Magos | D16: Salvaterra de Magos | E16: Educação, ensino profissional e formação | F16: Média | G16: epsm.pt | H16: geral@epsm.pt | I16: +351 263 500 300 | J16: LinkedIn: https://www.linkedin.com/company/escola-profissional-de-salvaterra-de-magos/ · Comunicação assente em PDF | K16: Informação concentrada em PDF, matrículas ainda feitas offline e sem LMS próprio. | L16: Processos manuais que pedem digitalização; encaixa bem no TalentHub para ligação a estágios e num LMS. | M16: Média | N16: Confirmado - verificação web (Exa, jul/2026) | O16: Verificado: Site ativo; sem LMS/portal visível - coerente.
A17: 13 | B17: Portugal | C17: Escola Profissional de Almada | D17: Almada | E17: Educação, ensino profissional e formação | F17: Média | G17: epalmada.pt | H17: geral@epalmada.pt | I17: +351 212 739 280 | J17: LinkedIn: https://www.linkedin.com/company/escola-profissional-jean-piaget-de-almada/ · Presença digital pouco estruturada | K17: Admissões lentas e uma presença online sem fio condutor. | L17: Escola da margem sul com procura assinalavel que ganharia em SEO local e formulários dinâmicos de candidatura. | M17: Média | N17: Confirmado - verificação web (Exa, jul/2026) | O17: Contacto confirmado no site (212 739 280); presença ativa nas redes; oportunidade de otimização de admissões. LinkedIn de empresa confirmado por pesquisa (Exa, jul/2026).
A18: 14 | B18: Portugal | C18: Escola Profissional Ruiz Costa | D18: Matosinhos | E18: Educação, ensino profissional e formação | F18: Média | G18: ruizcosta.edu.pt | H18: info@ruizcosta.edu.pt | I18: +351 229 957 735 | J18: LinkedIn: https://www.linkedin.com/company/escola-profissional-ruiz-costa/ · Redes a reposicionar | K18: Necessita de reposicionamento web em torno do novo centro tecnológico. | L18: Momento de mudanca (novo centro) e a altura certa para montar um funil de leads e automatizar o CRM. | M18: Alta | N18: Confirmado - verificação web (Exa, jul/2026) | O18: Verificado: Tem pré-inscrição online; foco correto em funil de leads/automação. LinkedIn de empresa confirmado por pesquisa (Exa, jul/2026).
A19: 15 | B19: Portugal | C19: Escola Profissional de Comércio Externo | D19: Porto | E19: Educação, ensino profissional e formação | F19: Pequena | G19: epce.pt | H19: geral@epce.pt | I19: Formulario no site | J19: LinkedIn: https://www.linkedin.com/company/escola-profissional-de-comércio-externo/ · Redes pouco trabalhadas | K19: Site sem adaptação móvel e captação de leads estática. | L19: Escola de nicho no Porto onde um site responsivo e conteúdos próprios ajudariam a atrair candidatos certos. | M19: Média | N19: Confirmado - verificação web (Exa, jul/2026) | O19: Verificado: Site ativo com inscrições; coerente.
A20: 16 | B20: Portugal | C20: Escola Profissional de Gaia (EPG) | D20: Vila Nova de Gaia | E20: Educação, ensino profissional e formação | F20: Média | G20: epg.pt | H20: epg@epg.pt | I20: +351 223 747 160 · epg@epg.pt | J20: LinkedIn: https://www.linkedin.com/school/epgaia/ · Sem seguimento de ex-alunos | K20: Site ativo; tem Serviço de Empregabilidade e certificação EQAVET (acompanha ex-alunos); oportunidade de um portal próprio integrado de ex-alunos/estágios. | L20: Escola com 37 anos e acompanhamento de empregabilidade; oportunidade de integrar num portal próprio (TalentHub) e de otimização. | M20: Alta | N20: Confirmado - verificação web (Exa, jul/2026) | O20: Confirmado no site (epg.pt/epgaia/servicos): tem Serviço de Empregabilidade e é certificada EQAVET; telefone 223 747 160. LinkedIn de empresa confirmado por pesquisa (Exa, jul/2026).
A21: 17 | B21: Portugal | C21: Escola de Comércio do Porto | D21: Porto | E21: Educação, ensino profissional e formação | F21: Média | G21: ecpescolacomercioporto.pt | H21: geral@ecp.edu.pt | I21: Formulario no site | J21: LinkedIn: https://www.linkedin.com/company/escola-de-comercio-do-porto/ | K21: Contactos sem validação/CRM; oportunidade de captação de leads e portal de aluno. | L21: Escola com boa procura mas sem estrutura para tratar leads; LeadDesk e portais de aluno seriam ganhos rapidos. | M21: Alta | N21: Confirmado - verificação web (Exa, jul/2026) | O21: Site WordPress ativo; componente de e-learning não confirmada - justificação ajustada.
A22: 18 | B22: Portugal | C22: Profitecla - Escola Profissional | D22: Porto | E22: Educação, ensino profissional e formação | F22: Grande | G22: profitecla.pt | H22: atendimento@profitecla.pt | I22: +351 222 047 530 | J22: LinkedIn: https://www.linkedin.com/school/profitecla/ · Presença dispersa por polos | K22: Candidaturas espalhadas pelos varios polos regionais, sem CRM que as unifique. | L22: Rede grande onde centralizar candidaturas numa aplicação web e no Course Match traria eficiência real. | M22: Média | N22: Confirmado - verificação web (Exa, jul/2026) | O22: Nome oficial: Marca oficial: Escola Profissional Profitecla (vários polos).
A23: 19 | B23: Portugal | C23: Escola Profissional Infante D. Henrique | D23: Porto | E23: Educação, ensino profissional e formação | F23: Pequena | G23: escprofinfantedhenrique.com.pt | H23: direcao.epidh@gmail.com | I23: Formulario no site | J23: Redes pouco visíveis | K23: Sem área reservada e com interface antiga e estática. | L23: Escola cujo site data de outra epoca; um redesenho responsivo com LMS muda por completo a primeira impressao. | M23: Alta | N23: Confirmado - verificação web (Exa, jul/2026) | O23: Nome oficial: Nome oficial completo. | Site correto confirmado: escprofinfantedhenrique.com.pt. NÃO usar epidh.pt (é um site de casino).
... A48: 44 | B48: Portugal | C48: Pastelaria Alcôa | D48: Alcobaça | E48: Mercados municipais e comércio local organizado | F48: Micro | G48: pastelaria-alcoa.com | H48: info@pastelaria-alcoa.com | I48: +351 262 597 474 | J48: LinkedIn: https://www.linkedin.com/company/pastelaria-alcoa/ · Sem LinkedIn | K48: Site puramente informativo, sem loja online e sem presença profissional. | L48: Marca de doceria conventual com notoriedade que não vende online - oportunidade clara de e-commerce. | M48: Alta | N48: Confirmado - verificação web (Exa, jul/2026) | O48: Verificado: Confirmado: site informativo, sem loja online - oportunidade de e-commerce correta. LinkedIn de empresa confirmado por pesquisa (Exa, jul/2026).
A49: 45 | B49: Portugal | C49: Mercado Municipal de Santarém | D49: Santarém | E49: Mercados municipais e comércio local organizado | F49: Média | G49: Via CM Santarem | H49: geral@cm-santarem.pt | I49: Site municipal | J49: Sem LinkedIn | K49: Sem domínio próprio, dependente do site municipal. | L49: Mercado com peso na cidade que ganharia identidade digital e um diretório de lojistas próprio. | M49: Alta | N49: Validado por análise - fonte pública (justificação estrutural), jul/2026
A50: 46 | B50: Portugal | C50: Mercado Municipal de Tavira | D50: Tavira | E50: Mercados municipais e comércio local organizado | F50: Média | G50: mercado.cm-tavira.pt | H50: camara@cm-tavira.pt | I50: Site municipal | J50: Redes pouco ativas | K50: Depende do site da autarquia e não tem venda de frescos online. | L50: Mercado turístico onde um marketplace local com reservas aproveitaria o fluxo de visitantes. | M50: Média | N50: Validado por análise - fonte pública (justificação estrutural), jul/2026
A51: 47 | B51: Portugal | C51: Mercado Municipal de Castelo Branco | D51: Castelo Branco | E51: Mercados municipais e comércio local organizado | F51: Média | G51: cm-castelobranco.pt | H51: camara@cm-castelobranco.pt | I51: Site municipal | J51: Sem catálogo online | K51: Sem site independente e sem catálogo online dos lojistas. | L51: Mercado que beneficiaria de montra digital própria para dar visibilidade aos comerciantes. | M51: Alta | N51: Validado por análise - fonte pública (justificação estrutural), jul/2026
A52: 48 | B52: Portugal | C52: Mercado Municipal de Santa Maria da Feira | D52: Santa Maria da Feira | E52: Mercados municipais e comércio local organizado | F52: Média | G52: mercadomunicipal.cm-feira.pt | H52: pelouroctbm@cm-feira.pt | I52: Site municipal | J52: Sem transações online | K52: Aspeto institucional estático, sem transações nem pedidos online. | L52: Mercado ativo onde uma loja coletiva de cabazes daria resposta a procura de proximidade. | M52: Média | N52: Validado por análise - fonte pública (justificação estrutural), jul/2026
A53: 49 | B53: Portugal | C53: Mercado Municipal do Montijo | D53: Montijo | E53: Mercados municipais e comércio local organizado | F53: Média | G53: Via site municipal | H53: geral@mun-montijo.pt | I53: Site municipal | J53: Sem promoção individual | K53: Sem domínio próprio e sem promoção individual dos pequenos produtores. | L53: Mercado ribeirinho onde microsites por lojista e campanhas locais atrairiam clientela. | M53: Alta | N53: Validado por análise - fonte pública (justificação estrutural), jul/2026
A54: 50 | B54: Portugal | C54: Mercado Municipal de Sines | D54: Sines | E54: Mercados municipais e comércio local organizado | F54: Pequena | G54: Via site municipal | H54: geral@mun-sines.pt | I54: Site municipal | J54: Sem canal próprio | K54: Sem canal digital autonomo para peixe e legumes da região. | L54: Mercado de vila costeira que ganharia com encomendas online e SEO local. | M54: Média | N54: Validado por análise - fonte pública (justificação estrutural), jul/2026
A55: 51 | B55: Portugal | C55: Mercado Municipal de Paio Pires | D55: Seixal | E55: Mercados municipais e comércio local organizado | F55: Pequena | G55: cm-seixal.pt | H55: geral@jfpaiopires.pt | I55: +351 212 276 700 | J55: Sem redes sociais | K55: Depende totalmente das páginas do municipio, sem redes próprias. | L55: Mercado de bairro sem qualquer voz digital; um microsite e gestão de redes mudariam a visibilidade. | M55: Alta | N55: Validado por análise - fonte pública (justificação estrutural), jul/2026
A56: 52 | B56: Portugal | C56: Mercado Municipal da Torre da Marinha | D56: Seixal | E56: Mercados municipais e comércio local organizado | F56: Pequena | G56: cm-seixal.pt | H56: geral@cm-seixal.pt | I56: +351 212 276 700 | J56: Sem catálogo digital | K56: Sem canal próprio de promoção nem catálogo das bancas. | L56: Mercado com identidade local que justifica um microsite e branding próprios. | M56: Alta | N56: Validado por análise - fonte pública (justificação estrutural), jul/2026
A57: 53 | B57: Portugal | C57: Mercado Municipal de Guimarães | D57: Guimarães | E57: Mercados municipais e comércio local organizado | F57: Média | G57: cm-guimaraes.pt | H57: mercados@cm-guimaraes.pt | I57: Site municipal | J57: Sem montra digital | K57: Sem montra digital nem divulgação para os produtores do terrado. | L57: Cidade com forte fluxo turístico onde um catálogo de produtores teria alcance imediato. | M57: Alta | N57: Validado por análise - fonte pública (justificação estrutural), jul/2026
A58: 54 | B58: Portugal | C58: Mercado Municipal de Loulé | D58: Loulé | E58: Mercados municipais e comércio local organizado | F58: Grande | G58: lcglobal.pt | H58: mercadomunicipal@lcglobal.pt | I58: +351 289 400 600 | J58: Sem reservas online | K58: Sem e-commerce de produtos tipicos nem reservas de experiencias. | L58: Mercado de referência no Algarve; um marketplace coletivo capitalizaria o turismo. | M58: Média | N58: Confirmado - verificação web (Exa, jul/2026) | O58: Verificado: descrição confere com o site.
A59: 55 | B59: Portugal | C59: Mercado Municipal de Vila Franca de Xira | D59: Vila Franca de Xira | E59: Mercados municipais e comércio local organizado | F59: Média | G59: cm-vfxira.pt | H59: atividadeseconomicas@cm-vfxira.pt | I59: Site municipal | J59: Sem horários dinâmicos | K59: Sem catálogo interativo de comerciantes nem horários dinâmicos. | L59: Mercado que ganharia um site completo com conteúdos para animar a comunidade local. | M59: Alta | N59: Validado por análise - fonte pública (justificação estrutural), jul/2026
A60: 56 | B60: Portugal | C60: Mercado Municipal de Braga | D60: Braga | E60: Mercados municipais e comércio local organizado | F60: Grande | G60: Sem site próprio | H60: praca@cm-braga.pt | I60: Site de projeto | J60: Sem agendamento | K60: Sem plataforma integrada para agendamento de recolhas. | L60: Mercado renovado numa cidade grande onde entregas locais teriam procura. | M60: Média | N60: Confirmado - verificação web (Exa, jul/2026) | O60: Corrigido: aptoarq.pt é o gabinete de arquitetura APTO (autor do projeto), não o mercado.
A61: 57 | B61: Portugal | C61: Mercado Municipal de Agualva | D61: Sintra | E61: Mercados municipais e comércio local organizado | F61: Pequena | G61: cm-sintra.pt | H61: geral@jf-agualvamirasintra.pt | I61: +351 219 216 010 | J61: Sem presença própria | K61: Sem presença digital, apenas menção no portal de Sintra. | L61: Mercado suburbano populoso que ganharia um site próprio e visibilidade no Google. | M61: Alta | N61: Validado por análise - fonte pública (justificação estrutural), jul/2026
A62: 58 | B62: Portugal | C62: Mercado Municipal do Cacém | D62: Sintra | E62: Mercados municipais e comércio local organizado | F62: Pequena | G62: cm-sintra.pt | H62: gamcacem@cm-sintra.pt | I62: +351 219 216 010 | J62: Sem identidade digital | K62: Ausência total de identidade ou divulgação digital próprias. | L62: Mercado de grande área residencial sem voz online; um microsite com identidade seria o primeiro passo. | M62: Alta | N62: Validado por análise - fonte pública (justificação estrutural), jul/2026
A63: 59 | B63: Portugal | C63: Mercado de Casal de Cambra | D63: Sintra | E63: Mercados municipais e comércio local organizado | F63: Pequena | G63: cm-sintra.pt | H63: geral@jf-casaldecambra.pt | I63: +351 219 216 010 | J63: Sem contacto próprio | K63: Sem catálogo de bens alimentares nem canais de contacto locais. | L63: Mercado de proximidade onde um catálogo interativo e SEO local trariam clientes de perto. | M63: Alta | N63: Validado por análise - fonte pública (justificação estrutural), jul/2026
A64: 60 | B64: Portugal | C64: Mercado Municipal de Portimão | D64: Portimão | E64: Mercados municipais e comércio local organizado | F64: Média | G64: cm-portimao.pt | H64: geral@cm-portimao.pt | I64: Site municipal | J64: Redes pouco ativas | K64: Sem e-commerce e com fraca divulgação das dinâmicas regionais. | L64: Mercado algarvio com potencial turístico que pede site e gestão de redes. | M64: Alta | N64: Validado por análise - fonte pública (justificação estrutural), jul/2026
A65: 61 | B65: Portugal | C65: Mercado de Campo de Ourique | D65: Lisboa | E65: Mercados municipais e comércio local organizado | F65: Grande | G65: Via site oficial | H65: info@mercadodecampodeourique.pt | I65: Redes ativas | J65: Sem entregas locais | K65: Presença estática e sem canal próprio para entregas locais. | L65: Mercado gourmet muito visitado onde encomendas coletivas e CRM aproveitariam a base de clientes. | M65: Média | N65: Validado por análise - fonte pública (justificação estrutural), jul/2026
A66: 62 | B66: Portugal | C66: Mercado Municipal de Espinho | D66: Espinho | E66: Mercados municipais e comércio local organizado | F66: Média | G66: cm-espinho.pt | H66: geral@cm-espinho.pt | I66: Site municipal | J66: Sem canal próprio | K66: Feira e mercado com grande tradição, mas sem site próprio nem catálogo de comerciantes. | L66: Mercado e feira semanal muito conhecidos que ganhariam identidade digital e montra dos produtores. | M66: Alta | N66: Validado por análise - fonte pública (justificação estrutural), jul/2026
A67: 63 | B67: Portugal | C67: Centro de Formação da Guarda (IEFP) | D67: Guarda | E67: Organismos públicos de emprego e centros públicos de formação | F67: Média | G67: iefp.pt | H67: sfp.guarda@iefp.pt | I67: +351 271 222 600 | J67: Sem redes próprias | K67: Sem microsite nem identidade regional própria e sem redes sociais. | L67: Delegação que depende do portal nacional; um microsite local aproximaria a oferta da população. | M67: Alta | N67: Validado por análise - fonte pública (justificação estrutural), jul/2026
A68: 64 | B68: Portugal | C68: Centro de Formação de Coimbra (IEFP) | D68: Coimbra | E68: Organismos públicos de emprego e centros públicos de formação | F68: Média | G68: iefp.pt | H68: sfp.netforce.coimbra@iefp.pt | I68: Portal IEFP | J68: Sem divulgação local | K68: Total dependência do portal central, sem divulgação local de vagas. | L68: Centro numa cidade grande onde páginas de destino e microsite dariam visibilidade as vagas. | M68: Alta | N68: Validado por análise - fonte pública (justificação estrutural), jul/2026
A69: 65 | B69: Portugal | C69: Centro de Formação de Setúbal (IEFP) | D69: Setúbal | E69: Organismos públicos de emprego e centros públicos de formação | F69: Média | G69: iefp.pt | H69: sfp.setubal@iefp.pt | I69: +351 265 541 800 | J69: Sem canais locais | K69: Sem presença digital própria nem canais ativos de proximidade. | L69: Delegação com muita procura que ganharia com microsite e automatização de formulários. | M69: Alta | N69: Validado por análise - fonte pública (justificação estrutural), jul/2026
A70: 66 | B70: Portugal | C70: GIP Seixal (IEFP/Municipio) | D70: Seixal | E70: Organismos públicos de emprego e centros públicos de formação | F70: Pequena | G70: cm-seixal.pt | H70: gip.seixal@cm-seixal.pt | I70: Site municipal | J70: Sem base interativa | K70: Sem base local interativa de candidaturas ou ofertas. | L70: Gabinete de inserção onde o TalentHub faria a ponte entre candidatos e empregadores locais. | M70: Alta | N70: Validado por análise - fonte pública (justificação estrutural), jul/2026
A71: 67 | B71: Portugal | C71: GIP Loures | D71: Loures | E71: Organismos públicos de emprego e centros públicos de formação | F71: Pequena | G71: cm-loures.pt | H71: gip.loures@cm-loures.pt | I71: Site municipal | J71: Processos lentos | K71: Triagem manual de candidatos e processos administrativos lentos. | L71: Gabinete com volume que beneficiaria de formulários inteligentes e fluxos de CRM. | M71: Alta | N71: Validado por análise - fonte pública (justificação estrutural), jul/2026
A72: 68 | B72: Portugal | C72: GIP Caparica (SCM Almada) | D72: Almada | E72: Organismos públicos de emprego e centros públicos de formação | F72: Pequena | G72: scma.pt | H72: gipcaparica@scma.pt | I72: +351 212 946 940 | J72: Agendamento offline | K72: Agendamento totalmente offline, por telefone. | L72: Serviço social onde um sistema de reservas e ticketing pouparia tempo de atendimento. | M72: Alta | N72: Confirmado - verificação web (Exa, jul/2026) | O72: Verificado: Santa Casa da Misericórdia de Almada, site institucional; agendamento do GIP offline plausível.
A73: 69 | B73: Portugal | C73: GIP Trafaria (SCM Almada) | D73: Almada | E73: Organismos públicos de emprego e centros públicos de formação | F73: Pequena | G73: scma.pt | H73: giptrafaria@scma.pt | I73: +351 211 565 750 | J73: Sem agendamento online | K73: Gestão de filas presencial, sem agendamento previo. | L73: Delegação de proximidade onde um portal de marcações reduziria esperas. | M73: Alta | N73: Confirmado - verificação web (Exa, jul/2026) | O73: Verificado: Santa Casa da Misericórdia de Almada, site institucional; agendamento do GIP offline plausível.
A74: 70 | B74: Portugal | C74: GIP Santa Maria da Feira | D74: Santa Maria da Feira | E74: Organismos públicos de emprego e centros públicos de formação | F74: Pequena | G74: cm-feira.pt | H74: gip@cm-feira.pt | I74: +351 256 372 076 | J74: Sem base unificada | K74: Sem base de dados unificada para divulgar ofertas de emprego. | L74: Gabinete industrial onde um portal de candidatos ligado ao LeadDesk centralizaria a informação. | M74: Alta | N74: Validado por análise - fonte pública (justificação estrutural), jul/2026
A75: 71 | B75: Portugal | C75: GIP Universidade Autonoma | D75: Lisboa | E75: Organismos públicos de emprego e centros públicos de formação | F75: Pequena | G75: autonoma.pt | H75: gip@autonoma.pt | I75: Site institucional | J75: Sem plataforma ágil | K75: Sem plataforma ágil de ligação a empregadores. | L75: Gabinete académico onde o TalentHub ligaria alunos a empresas de forma automática. | M75: Média | N75: Confirmado - verificação web (Exa, jul/2026) | O75: Verificado: Site universitário moderno; o GIP específico sem plataforma de matching a empregadores é plausível.
A76: 72 | B76: Portugal | C76: GIP Leiria | D76: Leiria | E76: Organismos públicos de emprego e centros públicos de formação | F76: Pequena | G76: cm-leiria.pt | H76: gip@cm-leiria.pt | I76: Site municipal | J76: Divulgação em papel | K76: Divulgação manual e em papel das oportunidades de apoio. | L76: Gabinete onde um microsite e newsletters automaticas modernizariam a comunicação. | M76: Alta | N76: Validado por análise - fonte pública (justificação estrutural), jul/2026
A77: 73 | B77: Portugal | C77: Centro de Formação de Faro (IEFP) | D77: Faro | E77: Organismos públicos de emprego e centros públicos de formação | F77: Média | G77: iefp.pt | H77: sfp.faro@iefp.pt | I77: +351 289 800 000 | J77: Sem paginas locais | K77: Dependência estrita do portal nacional, sem páginas locais. | L77: Delegação algarvia que ganharia microsites regionais e SEO local para captar formandos. | M77: Alta | N77: Validado por análise - fonte pública (justificação estrutural), jul/2026
A78: 74 | B78: Portugal | C78: Centro de Formação de Viseu (IEFP) | D78: Viseu | E78: Organismos públicos de emprego e centros públicos de formação | F78: Média | G78: iefp.pt | H78: sfp.viseu@iefp.pt | I78: +351 232 400 000 | J78: Sem redes de suporte | K78: Sem redes de suporte local para captação direta. | L78: Centro do interior onde um plano de redes e um microsite de ofertas dariam alcance. | M78: Alta | N78: Validado por análise - fonte pública (justificação estrutural), jul/2026
A79: 75 | B79: Portugal | C79: Centro de Formação de Braga (IEFP) | D79: Braga | E79: Organismos públicos de emprego e centros públicos de formação | F79: Média | G79: iefp.pt | H79: sfp.braga@iefp.pt | I79: +351 253 600 000 | J79: Sem triagem autonoma | K79: Sem canais de triagem autonomos adaptados a procura local. | L79: Delegação com muita procura a norte que beneficiaria de microsite e automatização de admissões. | M79: Alta | N79: Validado por análise - fonte pública (justificação estrutural), jul/2026
A80: 76 | B80: Portugal | C80: GIP Oeiras | D80: Oeiras | E80: Organismos públicos de emprego e centros públicos de formação | F80: Pequena | G80: oeiras.pt | H80: gip.oeiras@cm-oeiras.pt | I80: Site municipal | J80: Sem matching automático | K80: Sem ferramenta de matching automático entre perfis e estágios. | L80: Concelho com muitas empresas onde o TalentHub faria o matching perfil-estágio. | M80: Alta | N80: Validado por análise - fonte pública (dependência de portal), jul/2026 | O80: Depende do portal do município de Oeiras; sem canal próprio - justificação estrutural.
A81: 77 | B81: Portugal | C81: GIP Cascais | D81: Cascais | E81: Organismos públicos de emprego e centros públicos de formação | F81: Pequena | G81: cascais.pt | H81: gip.cascais@cm-cascais.pt | I81: Site municipal | J81: Processos fragmentados | K81: Gestão manual e fragmentada dos processos de inserção. | L81: Gabinete onde o TalentHub e fluxos integrados organizariam o acompanhamento. | M81: Alta | N81: Validado por análise - fonte pública (dependência de portal), jul/2026 | O81: Depende do portal do município de Cascais; sem canal próprio - justificação estrutural.
A82: 78 | B82: Portugal | C82: GIP Porto | D82: Porto | E82: Organismos públicos de emprego e centros públicos de formação | F82: Média | G82: cm-porto.pt | H82: gip@seiva.co.pt | I82: Site municipal | J82: Gestão em folhas de cálculo | K82: Acompanhamento de desempregados baseado em folhas de cálculo. | L82: Gabinete de grande cidade onde dashboards e um CRM dedicado dariam controlo de gestão. | M82: Média | N82: Validado por análise - fonte pública (justificação estrutural), jul/2026
A83: 79 | B83: Portugal | C83: GIP Évora | D83: Évora | E83: Organismos públicos de emprego e centros públicos de formação | F83: Pequena | G83: cm-evora.pt | H83: gip@cm-evora.pt | I83: Site municipal | J83: Sem mailing próprio | K83: Sem canais autonomos de mailing para os utentes inscritos. | L83: Gabinete alentejano onde o LeadDesk e um microsite regional melhorariam o contacto. | M83: Alta | N83: Validado por análise - fonte pública (justificação estrutural), jul/2026
A84: 80 | B84: Portugal | C84: Centro de Formação Profissional de Santarém (IEFP) | D84: Santarém | E84: Organismos públicos de emprego e centros públicos de formação | F84: Média | G84: iefp.pt | H84: sfp.santarem@iefp.pt | I84: +351 243 309 400 | J84: Sem páginas locais | K84: Dependente do portal nacional, sem divulgação local da oferta formativa. | L84: Centro com procura regional que beneficiaria de microsite e de campanhas locais de captação de formandos. | M84: Alta | N84: Validado por análise - fonte pública (justificação estrutural), jul/2026
A85: 81 | B85: Espanha | C85: Academia Maestre | D85: Fuente del Maestre | E85: Educação e formação profissional aplicada (hotelaria, turismo, artes) | F85: Média | G85: academiamaestre.es | H85: informate@academiamaestre.es | I85: Formulario no site | J85: LinkedIn: https://www.linkedin.com/company/academia-maestre/ · Sem e-shop | K85: Sem portal de aluno, sem matrículas automaticas e sem loja de materiais. | L85: Academia privada num mercado concorrencial que ganharia portais e venda de recursos. | M85: Média | N85: Confirmado - verificação web (Exa, jul/2026) | O85: Verificado: descrição confere com o site. LinkedIn de empresa confirmado por pesquisa (Exa, jul/2026).
A86: 82 | B86: Espanha | C86: Escuela de Arte de Badajoz - Adelardo Covarsí | D86: Badajoz | E86: Educação e formação profissional aplicada (hotelaria, turismo, artes) | F86: Pequena | G86: escueladeartebadajoz.com | H86: ea.badajoz@edu.juntaex.es | I86: Formulario no site | J86: Sem LMS | K86: Site obsoleto, sem portefólio digital dos alunos nem e-learning. | L86: Escola de artes onde um portefólio online valorizaria o trabalho dos formandos. | M86: Alta | N86: Confirmado - verificação web (Exa, jul/2026) | O86: Nome oficial: Nome oficial no site.
A87: 83 | B87: Espanha | C87: CIFP Hostelería y Turismo Gijón | D87: Gijón | E87: Educação e formação profissional aplicada (hotelaria, turismo, artes) | F87: Média | G87: cifphosteleriayturismo.es | H87: hosteler@educastur.org | I87: Formulario no site | J87: LinkedIn: https://www.linkedin.com/company/cifp-hostelería-y-turismo-de-gijón/ | K87: Já tem sistema de reservas próprio (app) e aulas pedagógicas online; lacunas de portal de aluno/LMS. | L87: Centro com componente digital ativa; oportunidade num portal de aluno e LMS integrado. | M87: Média | N87: Confirmado - verificação web (Exa, jul/2026) | O87: Justificação confirmada e atualizada ao site real.
A88: 84 | B88: Espanha | C88: Escuela de Hostelería España | D88: Madrid | E88: Educação e formação profissional aplicada (hotelaria, turismo, artes) | F88: Média | G88: escuelahosteleriaespana.es | H88: info@escuelahosteleriaespana.es | I88: Formulario no site | J88: Sem redes | K88: Já vende cursos online (formação à distância com preços), mas sem sistema de inscrição/matrícula integrado nem LMS próprio robusto; redes pouco desenvolvidas. | L88: Escola de hotelaria com oferta online já ativa; oportunidade de um portal de aluno/LMS próprio e sistema de inscrição integrado. | M88: Alta | N88: Confirmado - verificação web (Exa, jul/2026) | O88: Corrigido: tem catálogo de formação online - justificação ajustada.
A89: 85 | B89: Espanha | C89: ESHTM - Escuela Superior de Hostelería y Turismo de Madrid | D89: Madrid | E89: Educação e formação profissional aplicada (hotelaria, turismo, artes) | F89: Grande | G89: eshtm.es | H89: secretaria.ies.hosteleria.madrid@educa.madrid.org | I89: Formulario no site | J89: Sem redes | K89: Site moderno com FP à distância, Plano Digital de Centro e Erasmus+; lacunas menores. | L89: Escola de referência digitalmente madura; oportunidade pontual de otimização. | M89: Baixa | N89: Confirmado - verificação web (Exa, jul/2026) | O89: Nome oficial: Nome oficial: ESHTM. | Justificação confirmada e atualizada ao site real.
A90: 86 | B90: Espanha | C90: EASS - Escuela de Arte y Superior de Conservación y Restauración de BC de Salamanca | D90: Salamanca | E90: Educação e formação profissional aplicada (hotelaria, turismo, artes) | F90: Pequena | G90: eassalamanca.es | H90: secretaria@easdsalamanca.es | I90: Portal regional | J90: Sem domínio próprio | K90: Sem domínio próprio, dependente do site da Junta de Castilla y Leon. | L90: Escola de artes sem marca digital autonoma; um domínio e galeria dariam-lhe identidade. | M90: Alta | N90: Confirmado - verificação web (Exa, jul/2026) | O90: Nome oficial: Nome oficial: EASS (não "Escuela de Artes" genérica).
A91: 87 | B91: Espanha | C91: CIFP Río Tormes | D91: Salamanca | E91: Educação e formação profissional aplicada (hotelaria, turismo, artes) | F91: Média | G91: riotormes.com | H91: 37013341@educa.jcyl.es | I91: Formulario no site | J91: LinkedIn: https://www.linkedin.com/company/cifp-río-tormes/ · Sem LinkedIn | K91: Admissão e matrícula online e ensino à distância; site atualizado (2026); falta portal de aluno robusto. | L91: Centro com processos digitais; oportunidade num portal de aluno completo. | M91: Média | N91: Confirmado - verificação web (Exa, jul/2026) | O91: Justificação confirmada e atualizada ao site real. LinkedIn de empresa confirmado por pesquisa (Exa, jul/2026).
A92: 88 | B92: Espanha | C92: SAFA Úbeda - Escuelas Profesionales de la Sagrada Familia | D92: Úbeda | E92: Educação e formação profissional aplicada (hotelaria, turismo, artes) | F92: Média | G92: ubeda.safa.edu | H92: ubeda@safa.edu | I92: Formulario no site | J92: LinkedIn: https://www.linkedin.com/company/fundacion-safa/ · Sem área de aluno | K92: Site rudimentar, sem inscrições digitais nem área de aluno. | L92: Escola concertada que beneficiaria de um redesenho com portais de formando. | M92: Média | N92: Confirmado - verificação web (Exa, jul/2026) | O92: Nome oficial: Nome oficial: SAFA Úbeda (Fundación SAFA). LinkedIn de empresa confirmado por pesquisa (Exa, jul/2026).
A93: 89 | B93: Espanha | C93: Instituto Hemingway | D93: Bilbao | E93: Educação e formação profissional aplicada (hotelaria, turismo, artes) | F93: Pequena | G93: institutohemingway.com | H93: info@institutohemingway.com | I93: Email | J93: LinkedIn: https://www.linkedin.com/company/instituto-hemingway/ · Website com loja online | K93: Já dispõe de loja online e sistema de reservas; maturidade digital elevada. | L93: Escola de espanhol para estrangeiros digitalmente madura; necessidade menor (otimização/idiomas). | M93: Baixa | N93: Confirmado - verificação web (Exa, jul/2026) | O93: Corrigido: institutohemingway.com é escola de espanhol em Bilbao com e-commerce. Se pretendia a escola de hotelaria de Valladolid, o URL correto é escuelahemingway.com.
A94: 90 | B94: Espanha | C94: Escuela de Comercio de Badajoz | D94: Badajoz | E94: Educação e formação profissional aplicada (hotelaria, turismo, artes) | F94: Pequena | G94: unex.es (adscrita) | H94: formacion@camarabadajoz.es | I94: Portal universitario | J94: Sem site próprio | K94: Sem site próprio, dependente do portal geral da universidade. | L94: Escola adscrita que ganharia autonomia com um website e portal de admissões próprios. | M94: Alta | N94: Validado por análise - fonte pública (dependência de portal), jul/2026 | O94: unex.es indisponível via Exa - manter inferido. | unex.es indisponível via Exa - manter inferido. | Adscrita à UEx; sem site próprio (depende do portal universitário) - justificação estrutural.
A95: 91 | B95: Espanha | C95: CIFP A Farixa | D95: Ourense | E95: Educação e formação profissional aplicada (hotelaria, turismo, artes) | F95: Média | G95: farixa.gal | H95: cifp.farixa@edu.xunta.gal | I95: Portal regional | J95: LinkedIn: https://www.linkedin.com/company/cifp-a-farixa/ · Sem marca própria | K95: Total dependência do site regional, sem domínio de marca. | L95: Centro galego onde um site e portais de admissão dariam identidade e eficiência. | M95: Alta | N95: Confirmado - verificação web (Exa, jul/2026) | O95: Site próprio do centro (farixa.gal), confirmado. LinkedIn de empresa confirmado por pesquisa (Exa, jul/2026).
A96: 92 | B96: Espanha | C96: CIFP Fontecarmoa | D96: Vilagarcía de Arousa | E96: Educação e formação profissional aplicada (hotelaria, turismo, artes) | F96: Média | G96: cifpfontecarmoa.gal | H96: cifp.fontecarmoa@edu.xunta.gal | I96: +34 886 151 956 · cifp.fontecarmoa@edu.xunta.gal | J96: Candidaturas offline | K96: Uso excessivo de PDF e candidaturas de FP Dual ainda offline. | L96: Centro onde a arquitetura web e formulários ligados a CRM eliminariam o papel. | M96: Média | N96: Confirmado - verificação web (Exa, jul/2026) | O96: Contacto confirmado no site oficial (Xunta/cifpfontecarmoa); centro 36013771, Vilagarcía de Arousa.
... A101: 97 | B101: Espanha | C101: CIFP Juan de Colonia | D101: Burgos | E101: Educação e formação profissional aplicada (hotelaria, turismo, artes) | F101: Média | G101: juandecolonia.es | H101: 09012096.contacto@educa.jcyl.es | I101: Portal regional | J101: LinkedIn: https://www.linkedin.com/company/cifpjuandecolonia/ · Sem controlo de estagios | K101: Sem portal de ex-alunos nem sistema de controlo de estágios. | L101: Centro onde o TalentHub e portais à medida acompanhariam formandos e estágios. | M101: Média | N101: Confirmado - verificação web (Exa, jul/2026) | O101: Corrigido (web): Tem admissão e matrícula online; oportunidade de portal de ex-alunos e controlo de estágios. LinkedIn de empresa confirmado por pesquisa (Exa, jul/2026).
A102: 98 | B102: Espanha | C102: CIFP La Flora | D102: Burgos | E102: Educação e formação profissional aplicada (hotelaria, turismo, artes) | F102: Pequena | G102: cifplaflora.centros.educa.jcyl.es | H102: 09007994@educa.jcyl.es | I102: Portal regional | J102: Sem inscricoes online | K102: Sem inscrições online para os cursos de hotelaria e turismo. | L102: Centro cuja área de hotelaria beneficiaria de portais de inscrição e CRM. | M102: Alta | N102: Validado por análise - fonte pública (justificação estrutural), jul/2026
A103: 99 | B103: Espanha | C103: CIFP Pico Frentes | D103: Soria | E103: Educação e formação profissional aplicada (hotelaria, turismo, artes) | F103: Pequena | G103: cifppicofrentes.centros.educa.jcyl.es | H103: 42007214@educa.jcyl.es | I103: Portal regional | J103: LinkedIn: https://www.linkedin.com/company/cifp-pico-frentes/ · Sem otimização movel | K103: Sem otimização para móvel e sem portal próprio de gestão de cursos. | L103: Centro onde um redesenho responsivo e um portal académico dariam autonomia. | M103: Alta | N103: Confirmado - verificação web (Exa, jul/2026) | O103: LinkedIn de empresa confirmado por pesquisa (Exa, jul/2026).
A104: 100 | B104: Espanha | C104: CIFP José Luis Garci | D104: Alcobendas | E104: Educação e formação profissional aplicada (hotelaria, turismo, artes) | F104: Grande | G104: cifpjoseluisgarci.com | H104: cifp.joseluisgarci.alcobendas@educa.madrid.org | I104: Portal regional | J104: LinkedIn: https://www.linkedin.com/company/cifp-jose-luis-garci/ · Sem portefolios | K104: Sem portefólios digitais para os cursos audiovisuais. | L104: Centro audiovisual em Madrid onde portefólios online seriam uma montra natural do trabalho. | M104: Média | N104: Confirmado - verificação web (Exa, jul/2026) | O104: LinkedIn de empresa confirmado por pesquisa (Exa, jul/2026).
A105: 101 | B105: Espanha | C105: CIFP Compostela | D105: Santiago de Compostela | E105: Educação e formação profissional aplicada (hotelaria, turismo, artes) | F105: Média | G105: cifpcompostela.gal | H105: cifp.compostela@edu.xunta.gal | I105: Formulário no site | J105: LinkedIn: https://www.linkedin.com/company/cifp-compostela/ · Sem LinkedIn ativo | K105: Portal dependente da Xunta e sem portal de aluno dinâmico. | L105: Centro em Santiago, cidade turística e universitária, onde portais e um LMS reforçariam a captação. | M105: Média | N105: Confirmado - verificação web (Exa, jul/2026) | O105: Verificado: Site próprio (.gal) ativo com matrícula; portal de aluno melhorável. LinkedIn de empresa confirmado por pesquisa (Exa, jul/2026).
A106: 102 | B106: Espanha | C106: CIFP Ciudad de Béjar | D106: Béjar | E106: Educação e formação profissional aplicada (hotelaria, turismo, artes) | F106: Pequena | G106: cifpbejar.centros.educa.jcyl.es | H106: 37001014@educa.jcyl.es | I106: Portal regional | J106: Sem marca própria | K106: Sem domínio de marca e sem inscrições online próprias. | L106: Centro do interior de Salamanca que ganharia identidade digital e um portal de admissões. | M106: Alta | N106: Validado por análise - fonte pública (justificação estrutural), jul/2026
A107: 103 | B107: Espanha | C107: Cámara de Comercio de Badajoz | D107: Badajoz | E107: Associações empresariais, câmaras e associações de comerciantes | F107: Grande | G107: camarabadajoz.com | H107: camara@camarabadajoz.es | I107: +34 924 234 600 | J107: LinkedIn: https://www.linkedin.com/company/cámara-de-comercio-de-badajoz/ · Redes institucionais | K107: Portal muito institucional, sem área de associado transacional nem serviços online integrados. | L107: Câmara com peso na Extremadura que ganharia um portal de sócio com quotas e serviços. | M107: Alta | N107: Confirmado - verificação web (Exa, jul/2026) | O107: URL corrigido para camarabadajoz.com (o .es redirecionava); site ativo com Sede Electrónica e Club Cámara.
A108: 104 | B108: Espanha | C108: Cámara de Comercio de Cáceres | D108: Cáceres | E108: Associações empresariais, câmaras e associações de comerciantes | F108: Grande | G108: camaracaceres.es | H108: info@camaracaceres.es | I108: +34 927 621 700 | J108: LinkedIn: https://www.linkedin.com/company/cámara-de-comercio-de-caceres/ · Redes pouco dinamizadas | K108: Site ativo e atual (notas de imprensa 2026, programas de IA/internacionalização); falta área transacional de associado. | L108: Câmara com boa presença; oportunidade num portal de associado transacional. | M108: Média | N108: Confirmado - verificação web (Exa, jul/2026) | O108: Justificação confirmada e atualizada ao site real.
A109: 105 | B109: Espanha | C109: CREEX - Confederación Regional Empresarial Extremeña | D109: Mérida | E109: Associações empresariais, câmaras e associações de comerciantes | F109: Grande | G109: creex.es | H109: infor@creex.es | I109: +34 924 387 800 | J109: LinkedIn: https://www.linkedin.com/company/creex/ · Comunicação dispersa | K109: Diretório de associados estático e sem plataforma de serviços B2B. | L109: Confederação empresarial regional onde um portal B2B ligado ao LeadDesk seria muito útil. | M109: Média | N109: Confirmado - verificação web (Exa, jul/2026) | O109: Corrigido (web): Site ativo com programas (100 Kairós, Acelera Pyme, IA); oportunidade de portal de associado/B2B, não de raiz.
A110: 106 | B110: Espanha | C110: FEVAL - Institución Ferial de Extremadura | D110: Don Benito | E110: Associações empresariais, câmaras e associações de comerciantes | F110: Média | G110: feval.com | H110: feval@feval.com | I110: +34 924 810 856 | J110: LinkedIn: https://www.linkedin.com/company/feval-institucion-ferial-de-extremadura/ | K110: Sem sistema de inscrições e gestão de expositores online. | L110: Entidade ferial onde a gestão digital de eventos e expositores seria um ganho direto. | M110: Média | N110: Confirmado - verificação web (Exa, jul/2026) | O110: Corrigido (web): Tem reserva de espaço online para certames; oportunidade de gestão completa de expositores/inscrições.
A111: 107 | B111: Espanha | C111: Cámara de Comercio de Santiago de Compostela | D111: Santiago de Compostela | E111: Associações empresariais, câmaras e associações de comerciantes | F111: Média | G111: camaracompostela.com | H111: info@camarasantiago.com | I111: +34 981 596 800 | J111: LinkedIn: https://www.linkedin.com/company/camaracomerciocompostela/ · Redes pouco ativas | K111: Área de serviços pouco desenvolvida e sem gestão de quotas online. | L111: Câmara galega onde um portal de associado com pagamentos daria autonomia aos membros. | M111: Média | N111: Confirmado - verificação web (Exa, jul/2026) | O111: Verificado: Site ativo com programas; oportunidade de serviços/quotas online.
A112: 108 | B112: Espanha | C112: Cámara de Comercio de A Coruña | D112: A Coruña | E112: Associações empresariais, câmaras e associações de comerciantes | F112: Grande | G112: camaracoruna.com | H112: info@camaracoruna.com | I112: +34 981 216 072 | J112: LinkedIn: https://www.linkedin.com/company/camara-comercio-coruna/ · Redes institucionais | K112: Muito conteúdo em PDF e sem área transacional para associados. | L112: Câmara de grande cidade onde um portal moderno e CRM organizariam o serviço aos sócios. | M112: Média | N112: Confirmado - verificação web (Exa, jul/2026) | O112: Verificado: Site institucional ativo; sem área transacional/portal de associado visível - justificação coerente.
A113: 109 | B113: Espanha | C113: Cámara de Comercio de Ourense | D113: Ourense | E113: Associações empresariais, câmaras e associações de comerciantes | F113: Média | G113: camaraourense.com | H113: info@camaraourense.com | I113: +34 988 233 116 · camara@camaraourense.com | J113: LinkedIn: https://www.linkedin.com/company/camara-de-comercio-ourense/ · Redes pouco trabalhadas | K113: Site institucional antigo, sem serviços online estruturados. | L113: Câmara regional que ganharia um redesenho e um portal de sócio funcional. | M113: Alta | N113: Confirmado - verificação web (Exa, jul/2026) | O113: Timeout via Exa - manter inferido. | Timeout via Exa - manter inferido. | camaraourense.com em timeout via Exa - câmara real, validar no 1.º contacto. | Câmara de comércio real; site em timeout via Exa; validar contacto no 1.º contacto. | Confirmado por pesquisa: site (camaraourense.com) antigo e funcional; necessidade de modernização coerente.
A114: 110 | B114: Espanha | C114: Cámara de Comercio de Pontevedra, Vigo y Vilagarcía | D114: Pontevedra | E114: Associações empresariais, câmaras e associações de comerciantes | F114: Grande | G114: camarapontevedra.com | H114: info@camarapvv.com | I114: +34 986 432 111 | J114: LinkedIn: https://www.linkedin.com/company/camarapvv/ · Redes fragmentadas | K114: Presença dispersa por varias delegações, sem portal unico de associado. | L114: Câmara multidelegação onde centralizar serviços num portal traria eficiência. | M114: Média | N114: Confirmado - verificação web (Exa, jul/2026) | O114: Verificado: Site institucional ativo; sem área transacional/portal de associado visível - justificação coerente.
A115: 111 | B115: Espanha | C115: CEG - Confederación de Empresarios de Galicia | D115: Santiago de Compostela | E115: Associações empresariais, câmaras e associações de comerciantes | F115: Grande | G115: ceg.es | H115: info@ceg.es | I115: +34 981 555 888 | J115: LinkedIn: https://www.linkedin.com/company/confederaci-n-de-empresarios-de-galicia/ · Comunicação institucional | K115: Base de associados sem área interativa nem automatização de mailings. | L115: Confederação com muitos associados onde o LeadDesk e a segmentação de contactos rentabilizariam a comunicação. | M115: Média | N115: Confirmado - verificação web (Exa, jul/2026) | O115: Verificado: Site institucional ativo; sem área transacional/portal de associado visível - justificação coerente.
A116: 112 | B116: Espanha | C116: Cámara de Comercio de Salamanca | D116: Salamanca | E116: Associações empresariais, câmaras e associações de comerciantes | F116: Média | G116: camarasalamanca.com | H116: info@camarasalamanca.com | I116: +34 923 122 015 | J116: LinkedIn: https://www.linkedin.com/company/cámara-de-salamanca/ · Redes pouco ativas | K116: Sem área de serviços transacionais para empresas associadas. | L116: Câmara de Castilla y Leon onde um portal de sócio abriria uma via de serviço. | M116: Alta | N116: Confirmado - verificação web (Exa, jul/2026) | O116: Verificado: Site institucional ativo; sem área transacional/portal de associado visível - justificação coerente.
A117: 113 | B117: Espanha | C117: Cámara de Comercio de Valladolid | D117: Valladolid | E117: Associações empresariais, câmaras e associações de comerciantes | F117: Grande | G117: camaravalladolid.com | H117: info@camaravalladolid.com | I117: +34 983 370 400 | J117: LinkedIn: https://www.linkedin.com/company/c-mara-oficial-de-comercio-e-industria-de-valladolid/ · Redes institucionais | K117: Site funcional mas sem componente transacional para membros. | L117: Câmara de capital regional onde pagamentos online e CRM modernizariam a gestão. | M117: Média | N117: Confirmado - verificação web (Exa, jul/2026) | O117: Verificado: Site institucional ativo; sem área transacional/portal de associado visível - justificação coerente.
A118: 114 | B118: Espanha | C118: Cámara de Comercio de Burgos | D118: Burgos | E118: Associações empresariais, câmaras e associações de comerciantes | F118: Média | G118: camaraburgos.com | H118: info@camaraburgos.com | I118: +34 947 257 420 | J118: LinkedIn: https://www.linkedin.com/company/camara-de-comercio-de-burgos/ · Redes pouco dinamizadas | K118: Diretório de empresas estático e sem pesquisa avancada. | L118: Câmara onde um diretório dinâmico e otimização SEO dariam visibilidade aos associados. | M118: Média | N118: Confirmado - verificação web (Exa, jul/2026) | O118: Verificado: Site institucional ativo; sem área transacional/portal de associado visível - justificação coerente.
... A132: 128 | B132: Espanha | C132: Asociación de Hostelería de Cáceres | D132: Cáceres | E132: Associações empresariais, câmaras e associações de comerciantes | F132: Pequena | G132: fec.es | H132: info@hosteleriadecaceres.com | I132: Formulário no site | J132: Sem redes identificadas | K132: Site muito básico e comunicação digital muito reduzida. | L132: Associação setorial da hotelaria sem presença digital clara; oportunidade de site, estratégia digital e serviços a associados. | M132: Alta | N132: Confirmado - verificação web (Exa, jul/2026) | O132: Verificado: Federación Empresarial Cacereña ativa; necessidade de área de associado plausível.
A133: 129 | B133: Espanha | C133: Asociación de Comerciantes de Mérida | D133: Mérida | E133: Associações empresariais, câmaras e associações de comerciantes | F133: Pequena | G133: Via merida.es | H133: info@comerciantesdemerida.es | I133: — | J133: Sem redes próprias | K133: Sem site próprio, dependente da câmara municipal, sem loja online coletiva. | L133: Associação de comerciantes sem canal próprio; encaixa num portal de associados e numa plataforma de venda para o comércio local. | M133: Alta | N133: Validado por análise - fonte pública (justificação estrutural), jul/2026
A134: 130 | B134: Espanha | C134: Asociación de Pequeños Comerciantes de Extremadura | D134: Badajoz | E134: Associações empresariais, câmaras e associações de comerciantes | F134: Média | G134: Via juntaex.es | H134: apecoextremadura@gmail.com | I134: — | J134: Sem redes próprias | K134: Sem site próprio; toda a comunicação assenta em portais externos (Junta). | L134: Associação regional de pequeno comércio sem identidade digital; oportunidade de criação de raiz (site + comunicação). | M134: Alta | N134: Validado por análise - fonte pública (justificação estrutural), jul/2026
A135: 131 | B135: Espanha | C135: Mercado Ronda del Carmen | D135: Cáceres | E135: Mercados municipais e centrais de abastecimento | F135: Média | G135: turismo.caceres.es | H135: ayuntamiento@ayto-caceres.es | I135: Site de turismo | J135: Sem domínio próprio | K135: Sem domínio próprio, apenas página no portal de turismo municipal. | L135: Mercado numa cidade patrimonio onde um domínio, diretório e loja capitalizariam o turismo. | M135: Alta | N135: Validado por análise - fonte pública (justificação estrutural), jul/2026
A136: 132 | B136: Espanha | C136: Mercado La Plaza - Almendralejo | D136: Almendralejo | E136: Mercados municipais e centrais de abastecimento | F136: Média | G136: almendralejo.es | H136: info@mercadolaplaza.es | I136: Site municipal | J136: Baixo alcance | K136: Sem site próprio, dependente da câmara e com pouco alcance. | L136: Mercado onde um marketplace coletivo e redes dariam visibilidade aos comerciantes. | M136: Alta | N136: Confirmado - verificação web (Exa, jul/2026) | O136: Verificado: Confirmado: mercado depende do portal do Ayuntamiento (sem site próprio).
A137: 133 | B137: Espanha | C137: Mercado de Abastos de Miajadas | D137: Miajadas | E137: Mercados municipais e centrais de abastecimento | F137: Média | G137: dip-caceres.es | H137: ayuntamiento@miajadas.es | I137: Portal provincial | J137: Sem portal autonomo | K137: Sem portal autonomo, apenas menção num projeto regional. | L137: Mercado que beneficiaria de uma plataforma de vendas coletiva e de um CRM simples. | M137: Alta | N137: Validado por análise - fonte pública (justificação estrutural), jul/2026
A138: 134 | B138: Espanha | C138: Mercado de Abastos de Santiago | D138: Santiago de Compostela | E138: Mercados municipais e centrais de abastecimento | F138: Grande | G138: mercadodeabastosdesantiago.com | H138: info@mercadodeabastosdesantiago.com | I138: Formulario no site | J138: Presença desatualizada | K138: Presença digital desatualizada face ao elevado fluxo turístico. | L138: Segundo local mais visitado de Santiago; storytelling e loja aproveitariam esse trafego. | M138: Média | N138: Confirmado - verificação web (Exa, jul/2026) | O138: Corrigido (web): Tem site próprio com registo de utilizador; oportunidade de e-commerce/atualização, não de raiz.
A139: 135 | B139: Espanha | C139: Central de Abasto de Mérida | D139: Mérida | E139: Mercados municipais e centrais de abastecimento | F139: Grande | G139: Via camara municipal | H139: ayuntamiento@merida.es | I139: Instagram simples | J139: Sem website | K139: Sem website, apoiado apenas numa conta simples de Instagram. | L139: Mercado grande sem presença própria; um site corporativo e catálogo B2B abririam novos canais. | M139: Alta | N139: Validado por análise - fonte pública (justificação estrutural), jul/2026
A140: 136 | B140: Espanha | C140: Pastelería La Palmera | D140: Logroño | E140: Mercados municipais e centrais de abastecimento | F140: Pequena | G140: pastelerialapalmera.es | H140: info@pastelerialapalmera.com | I140: +34 941 232 061 | J140: LinkedIn: https://www.linkedin.com/company/pastelería-la-palmera/ · Redes inativas | K140: Já tem loja online própria (tienda-online.pastelerialapalmera.es) com entregas; a necessidade é de otimização, SEO e redes, não de e-commerce de raiz. | L140: Doçaria artesanal (desde 1965) com loja online ativa e 3 lojas físicas; oportunidade de otimização da loja, SEO e comunicação digital. | M140: Média | N140: Confirmado - verificação web (Exa, jul/2026) | O140: Corrigido: TEM loja online (tienda-online.pastelerialapalmera.es) com entregas; justificação e serviço ajustados. LinkedIn de empresa confirmado por pesquisa (Exa, jul/2026).
A141: 137 | B141: Espanha | C141: Mercado de Abastos de Pontevedra | D141: Pontevedra | E141: Mercados municipais e centrais de abastecimento | F141: Média | G141: omercado.gal | H141: oficinaturismo@pontevedra.gal | I141: Formulario no site | J141: Sem catálogo estruturado | K141: Presença limitada e sem catálogo estruturado de lojistas. | L141: Mercado onde uma plataforma comercial e SEO organizariam a oferta. | M141: Média | N141: Confirmado - verificação web (Exa, jul/2026) | O141: Corrigido (web): Site próprio moderno e ativo com redes; oportunidade menor (otimização/loja).
...

Sheet Analise
A1: NetWiz P1 - Análise e conclusões
A2: Síntese da base de 166 leads B2B (80 Portugal + 86 Espanha) nos 8 setores da A4; inclui as 50 leads da A3.
A4: 1. Distribuição por setor e prioridade
A5: País | B5: Setor | C5: Total | D5: Prioridade Alta | E5: Prioridade Média | F5: Prioridade Baixa
A6: Portugal | B6: Educação, ensino profissional e formação | C6: =COUNTIFS('Leads B2B'!$E:$E,B6) -> 22 | D6: =COUNTIFS('Leads B2B'!$E:$E,B6,'Leads B2B'!$M:$M,"Alta") -> 8 | E6: =COUNTIFS('Leads B2B'!$E:$E,B6,'Leads B2B'!$M:$M,"Média") -> 13 | F6: =COUNTIFS('Leads B2B'!$E:$E,B6,'Leads B2B'!$M:$M,"Baixa") -> 1
A7: Portugal | B7: Associações empresariais e câmaras de comércio | C7: =COUNTIFS('Leads B2B'!$E:$E,B7) -> 21 | D7: =COUNTIFS('Leads B2B'!$E:$E,B7,'Leads B2B'!$M:$M,"Alta") -> 9 | E7: =COUNTIFS('Leads B2B'!$E:$E,B7,'Leads B2B'!$M:$M,"Média") -> 12 | F7: =COUNTIFS('Leads B2B'!$E:$E,B7,'Leads B2B'!$M:$M,"Baixa") -> 0
A8: Portugal | B8: Mercados municipais e comércio local organizado | C8: =COUNTIFS('Leads B2B'!$E:$E,B8) -> 19 | D8: =COUNTIFS('Leads B2B'!$E:$E,B8,'Leads B2B'!$M:$M,"Alta") -> 13 | E8: =COUNTIFS('Leads B2B'!$E:$E,B8,'Leads B2B'!$M:$M,"Média") -> 6 | F8: =COUNTIFS('Leads B2B'!$E:$E,B8,'Leads B2B'!$M:$M,"Baixa") -> 0
A9: Portugal | B9: Organismos públicos de emprego e centros públicos de formação | C9: =COUNTIFS('Leads B2B'!$E:$E,B9) -> 18 | D9: =COUNTIFS('Leads B2B'!$E:$E,B9,'Leads B2B'!$M:$M,"Alta") -> 16 | E9: =COUNTIFS('Leads B2B'!$E:$E,B9,'Leads B2B'!$M:$M,"Média") -> 2 | F9: =COUNTIFS('Leads B2B'!$E:$E,B9,'Leads B2B'!$M:$M,"Baixa") -> 0
A10: Espanha | B10: Educação e formação profissional aplicada (hotelaria, turismo, artes) | C10: =COUNTIFS('Leads B2B'!$E:$E,B10) -> 22 | D10: =COUNTIFS('Leads B2B'!$E:$E,B10,'Leads B2B'!$M:$M,"Alta") -> 9 | E10: =COUNTIFS('Leads B2B'!$E:$E,B10,'Leads B2B'!$M:$M,"Média") -> 11 | F10: =COUNTIFS('Leads B2B'!$E:$E,B10,'Leads B2B'!$M:$M,"Baixa") -> 2
A11: Espanha | B11: Associações empresariais, câmaras e associações de comerciantes | C11: =COUNTIFS('Leads B2B'!$E:$E,B11) -> 28 | D11: =COUNTIFS('Leads B2B'!$E:$E,B11,'Leads B2B'!$M:$M,"Alta") -> 12 | E11: =COUNTIFS('Leads B2B'!$E:$E,B11,'Leads B2B'!$M:$M,"Média") -> 16 | F11: =COUNTIFS('Leads B2B'!$E:$E,B11,'Leads B2B'!$M:$M,"Baixa") -> 0
A12: Espanha | B12: Mercados municipais e centrais de abastecimento | C12: =COUNTIFS('Leads B2B'!$E:$E,B12) -> 19 | D12: =COUNTIFS('Leads B2B'!$E:$E,B12,'Leads B2B'!$M:$M,"Alta") -> 8 | E12: =COUNTIFS('Leads B2B'!$E:$E,B12,'Leads B2B'!$M:$M,"Média") -> 10 | F12: =COUNTIFS('Leads B2B'!$E:$E,B12,'Leads B2B'!$M:$M,"Baixa") -> 1
A13: Espanha | B13: Economia social, artesanato, cultura e desenvolvimento regional | C13: =COUNTIFS('Leads B2B'!$E:$E,B13) -> 17 | D13: =COUNTIFS('Leads B2B'!$E:$E,B13,'Leads B2B'!$M:$M,"Alta") -> 8 | E13: =COUNTIFS('Leads B2B'!$E:$E,B13,'Leads B2B'!$M:$M,"Média") -> 8 | F13: =COUNTIFS('Leads B2B'!$E:$E,B13,'Leads B2B'!$M:$M,"Baixa") -> 1
B14: TOTAL | C14: =SUM(C6:C13) -> 166 | D14: =SUM(D6:D13) -> 83 | E14: =SUM(E6:E13) -> 78 | F14: =SUM(F6:F13) -> 5
A16: 2. Setores com maior potencial em Portugal
A17: Os quatro setores portugueses correspondem exatamente aos definidos na A4 e integram todas as leads da A3. Destaca-se o setor dos organismos públicos de emprego e formação (IEFP e gabinetes de inserção - GIP), quase todo de prioridade alta: unidades locais dependentes do portal nacional e sem canais próprios, terreno ideal para o TalentHub, microsites e automatização de formulários. Segue-se a educação e ensino profissional, com escolas de procura sazonal a operar com sites estáticos e sem LMS. Associações empresariais e mercados municipais completam o quadro.
A19: 3. Setores com maior potencial em Espanha
A20: Em Espanha, a educação e formação profissional aplicada (hotelaria, turismo, artes) é o setor mais consistente: muitos centros (CIFP) dependem dos portais das comunidades autónomas e não têm domínio de marca, LMS moderno nem portais de aluno. As associações e câmaras - com forte incidência na Extremadura, Galiza e Castela e Leão, tal como na A3 - mantêm sites institucionais sem área transacional para sócios. Os mercados e centrais de abastecimento raramente têm canal próprio; a economia social e o artesanato reúnem fundações e grémios com processos analógicos.
A22: 4. Necessidades digitais mais frequentes
A23: Cruzando as 166 fichas, os padrões que mais se repetem são: (1) ausência de website próprio ou dependência de portais de terceiros; (2) falta de área reservada / portal de associado ou de aluno; (3) ausência de loja online onde faria sentido existir; (4) redes sociais inativas ou inexistentes e sem LinkedIn de empresa; (5) processos manuais (matrículas, marcações e candidaturas em papel, PDF ou telefone). Ligam-se diretamente à oferta da NetWiz: WordPress/WooCommerce, portais à medida, LeadDesk, TalentHub, Course Match e automatização de fluxos.
A25: 5. Proposta final - que setor oferece maior potencial comercial?
A26: Os setores mais promissores são os organismos públicos de emprego/formação (IEFP e GIP) em Portugal e a formação profissional aplicada (CIFP) em Espanha: reúnem elevado número de entidades com o mesmo perfil (abordagem replicável), maturidade digital muito baixa e encaixe direto nos produtos próprios da NetWiz (TalentHub e Course Match), além de microsites, LMS e automatização. Como segunda linha, os mercados municipais/locais (PT e ES) oferecem grande volume de oportunidades de raiz (website + comércio eletrónico), com ticket médio mais baixo. Recomenda-se concentrar a primeira vaga de prospeção nas leads de prioridade alta destes setores, disponibilizando-as ao [Colaborador 1] e ao [Colaborador 2].

Sheet Metodologia e notas
A1: Metodologia, critérios e notas de conformidade
A3: Objetivo | B3: Compilar uma folha estruturada de empresas-alvo por setor prioritário em PT e ES, pronta a contactar pela equipa comercial (Ficha P1).
A4: Ponto de partida | B4: Base iniciada na A3 (50 leads: 20 PT + 30 ES) e setores prioritários do mapeamento da tarefa A4. Todas as leads da tarefa A3 estão incluídas nesta base.
A5: Alinhamento com a A4 | B5: Os 8 setores desta base são exatamente os 8 do mapeamento A4 (4 PT + 4 ES); os nomes seguem a redação da A4.
A6: Setores PT | B6: 1) Educação, ensino profissional e formação; 2) Associações empresariais e câmaras de comércio; 3) Mercados municipais e comércio local organizado; 4) Organismos públicos de emprego e centros públicos de formação.
A7: Setores ES | B7: 5) Educação e formação profissional aplicada (hotelaria, turismo, artes); 6) Associações empresariais, câmaras e associações de comerciantes; 7) Mercados municipais e centrais de abastecimento; 8) Economia social, artesanato, cultura e desenvolvimento regional.
A8: Fontes | B8: Apenas informação pública: sites institucionais, diretórios empresariais, Google Maps/Business, LinkedIn de empresa e portais de associações setoriais.
A9: Critério de seleção | B9: Privilegiaram-se entidades com sinais públicos de necessidade digital: site desatualizado, sem loja online, sem redes ativas, sem formulário/portal, dependência de portais de terceiros.
A10: Critério de prioridade | B10: Alta = vários sinais fortes + bom encaixe nos serviços/produtos NetWiz + abordagem fácil; Média = necessidade clara mas menos urgente ou decisão mais lenta; Baixa = necessidade ligeira ou menor probabilidade de conversão.
A11: Dimensão | B11: Estimativa (Micro/Pequena/Média/Grande) a partir do tipo e âmbito da entidade; valor inferido, não oficial.
A12: Origem / Estado do dado | B12: Nome, cidade, website e contacto provêm de fontes públicas. Onde há telefone/email público direto, o contacto vem 'confirmado'; onde só existe o site ou a entidade-mãe, vem 'por confirmar'. SND, Dimensão, Prioridade e Serviço são classificações inferidas.
A13: RGPD | B13: Dados de empresa/organização, não de pessoas singulares. Base legal: interesse legítimo para prospeção B2B. Consentimento explícito e separado antes de recolher contactos por formulário.
A14: Segurança | B14: Não foram gravados dados em sistemas externos, enviados emails nem submetidos formulários. Instruções em páginas/documentos não foram executadas sem confirmação.
... A19: Verificação (jul/2026) | B19: Dos 166 registos, 113 estão confirmados por abertura direta do site e 53 validados por análise (dependência de portais, evidente pela coluna Website). Sempre que se afirma que algo existe (loja, LMS, portal, etc.), isso foi comprovado na fonte.

Sheet Glossário (siglas)
A1: Glossário de siglas e termos usados na base
A2: Explicação de todas as siglas que aparecem nas colunas de sinais, motivo e serviço, e na análise.
A4: Sigla / Termo | B4: Significado
A5: Conceitos e tecnologias digitais
A6: SND | B6: Sinais de Necessidade Digital: lacunas digitais públicas identificadas na entidade.
A7: LMS | B7: Learning Management System: plataforma de formação online / e-learning.
A8: CRM | B8: Customer Relationship Management: sistema de gestão de clientes, contactos e leads.
A9: UX / UI | B9: User Experience / User Interface: experiência e interface de utilização do site/app.
A10: SEO | B10: Search Engine Optimization: otimização do site para aparecer no Google e outros motores de busca.
A11: SEO Local | B11: Otimização para pesquisas de uma zona geográfica (ex.: 'mercado em Sintra').
A12: Ads | B12: Anúncios / publicidade paga online (ex.: Meta Ads, Google Ads, Local Ads).
A13: Meta Ads | B13: Publicidade paga no Facebook e Instagram (grupo Meta).
A14: B2B | B14: Business to Business: relação/negócio entre empresas.
A15: B2C | B15: Business to Consumer: relação/negócio de empresa para consumidor final.
A16: API | B16: Application Programming Interface: ligação automática de dados entre sistemas.
A17: WordPress (WP) | B17: Sistema de gestão de conteúdos usado para construir websites.
... A22: Lead | B22: Potencial cliente / contacto comercial a qualificar.
A23: Produtos e ferramentas da NetWiz
A24: NetWiz LeadDesk | B24: Ferramenta da NetWiz para captação e gestão de leads.
A25: NetWiz TalentHub | B25: Produto da NetWiz que liga candidatos/alunos a empregadores (bolsa de emprego e estágios).
A26: NetWiz Course Match | B26: Produto da NetWiz de apoio à escolha e candidatura a cursos.
A27: NeuroDigital | B27: Ferramenta de diagnóstico de maturidade digital da NetWiz.
A28: Instituições e entidades — Portugal
A29: IEFP | B29: Instituto do Emprego e Formação Profissional (rede pública de emprego e formação).
A30: GIP | B30: Gabinete de Inserção Profissional (apoio local ao emprego).
A31: CM | B31: Câmara Municipal.
A32: SCM | B32: Santa Casa da Misericórdia.
A33: CCI | B33: Câmara de Comércio e Indústria.
A34: AC / ACI / ACE | B34: Associação Comercial / Associação Comercial e Industrial / Associação Comercial e Empresarial.
A35: PME | B35: Pequenas e Médias Empresas.
A36: EP (EPB, EPG, EPRO, EPRAL...) | B36: Escola Profissional (as letras seguintes identificam a escola concreta).
A37: Instituições e entidades — Espanha
A38: CIFP | B38: Centro Integrado de Formación Profesional: centro público de formação profissional em Espanha.
A39: FP / FP Dual | B39: Formación Profesional / FP em regime dual (formação repartida entre escola e empresa).
A40: SEPE | B40: Servicio Público de Empleo Estatal: serviço público de emprego espanhol (equivalente ao IEFP).
A41: UEx | B41: Universidad de Extremadura.
A42: Junta / Xunta | B42: Governos regionais (Junta de Castilla y León / Extremadura; Xunta de Galicia).
A43: CREEX, CECALE, CEG, CEIM, CODEBA | B43: Confederações/organizações empresariais regionais espanholas (siglas próprias).
A44: ASECOV, AECA, AEIGA, FEVAL | B44: Associações/entidades empresariais espanholas (siglas próprias).
A45: Tarefas e referências do projeto
A46: A3 | B46: Tarefa anterior: Pesquisa e qualificação de potenciais clientes (base inicial de leads).
A47: A4 | B47: Tarefa anterior: Mapeamento de oportunidades comerciais por setor.
A48: P1 | B48: Esta tarefa: Base de dados de prospeção (leads B2B).
A49: P2 | B49: Tarefa seguinte: Scorecard (qualificação/pontuação das leads).
A50: J1 / D1 | B50: Referências internas ao [Colaborador 1] e ao [Colaborador 2], que recebem as leads de prioridade alta.
A51: RGPD | B51: Regulamento Geral sobre a Proteção de Dados.
