Workbook

Sheet Oferta Formativa PT
A1: Nome da Instituição | B1: País | C1: Cidade | D1: Tipo de Instituição (Pública/Privada) | E1: Tipologia do Curso | F1: Nome do Curso | G1: Área Científica | H1: Campus / Unidade / Faculdade | I1: Link Oficial do Curso | J1: Duração | K1: Modalidade | L1: Idioma | M1: Observações relevantes | N1: Região (análise)
A2: Atlântica – Instituto Universitário | B2: Portugal | C2: Oeiras | D2: Privada | E2: Licenciatura | F2: Ciências da Nutrição | G2: Terapia e Reabilitação | H2: Campus Atlântica, Fábrica da Pólvora de Barcarena | I2: https://www.google.com/search?q=site%3Auatlantica.pt%20Ci%C3%AAncias%20da%20Nutri%C3%A7%C3%A3o%20licenciatura | J2: 4 ano(s) (240 ECTS) | K2: Presencial | L2: Português | N2: A.M. Lisboa
A3: Atlântica – Instituto Universitário | B3: Portugal | C3: Oeiras | D3: Privada | E3: Licenciatura | F3: Design UX/UI | G3: Design | H3: Campus Atlântica, Fábrica da Pólvora de Barcarena | I3: https://www.google.com/search?q=site%3Auatlantica.pt%20Design%20UX/UI%20licenciatura | J3: 3 ano(s) (180 ECTS) | K3: Presencial | L3: Português | N3: A.M. Lisboa
A4: Atlântica – Instituto Universitário | B4: Portugal | C4: Oeiras | D4: Privada | E4: Licenciatura | F4: Engenharia Aeronáutica | G4: Construção e Reparação de Veículos a Motor (aeronáutica) | H4: Campus Atlântica, Fábrica da Pólvora de Barcarena | I4: https://www.google.com/search?q=site%3Auatlantica.pt%20Engenharia%20Aeron%C3%A1utica%20licenciatura | J4: 3 ano(s) (180 ECTS) | K4: Presencial | L4: Português | N4: A.M. Lisboa
A5: Atlântica – Instituto Universitário | B5: Portugal | C5: Oeiras | D5: Privada | E5: Licenciatura | F5: Engenharia Mecânica | G5: Metalurgia e Metalomecânica | H5: Campus Atlântica, Fábrica da Pólvora de Barcarena | I5: https://www.google.com/search?q=site%3Auatlantica.pt%20Engenharia%20Mec%C3%A2nica%20licenciatura | J5: 3 ano(s) (180 ECTS) | K5: Presencial | L5: Português | N5: A.M. Lisboa
A6: Atlântica – Instituto Universitário | B6: Portugal | C6: Oeiras | D6: Privada | E6: Licenciatura | F6: Engenharia de Materiais | G6: Metalurgia e Metalomecânica | H6: Campus Atlântica, Fábrica da Pólvora de Barcarena | I6: https://www.google.com/search?q=site%3Auatlantica.pt%20Engenharia%20de%20Materiais%20licenciatura | J6: 3 ano(s) (180 ECTS) | K6: Presencial | L6: Português | M6: Em processo de extinção | N6: A.M. Lisboa
A7: Atlântica – Instituto Universitário | B7: Portugal | C7: Oeiras | D7: Privada | E7: Licenciatura | F7: Gestão | G7: Gestão e Administração | H7: Campus Atlântica, Fábrica da Pólvora de Barcarena | I7: https://www.google.com/search?q=site%3Auatlantica.pt%20Gest%C3%A3o%20licenciatura | J7: 3 ano(s) (180 ECTS) | K7: Presencial | L7: Português | N7: A.M. Lisboa
A8: Atlântica – Instituto Universitário | B8: Portugal | C8: Oeiras | D8: Privada | E8: Licenciatura | F8: Gestão da Segurança, Emergência e Proteção Civil | G8: Proteção de Pessoas e Bens | H8: Campus Atlântica, Fábrica da Pólvora de Barcarena | I8: https://www.google.com/search?q=site%3Auatlantica.pt%20Gest%C3%A3o%20da%20Seguran%C3%A7a%2C%20Emerg%C3%AAncia%20e%20Prote%C3%A7%C3%A3o%20Civil%20licenciatura | J8: 3 ano(s) (180 ECTS) | K8: Presencial | L8: Português | N8: A.M. Lisboa
A9: Atlântica – Instituto Universitário | B9: Portugal | C9: Oeiras | D9: Privada | E9: Licenciatura | F9: Gestão de Sistemas e Computação | G9: Ciências Informáticas | H9: Campus Atlântica, Fábrica da Pólvora de Barcarena, 2730‑036 Barcarena, Oeiras | I9: https://www.google.com/search?q=site%3Auatlantica.pt%20Gest%C3%A3o%20de%20Sistemas%20e%20Computa%C3%A7%C3%A3o%20licenciatura | J9: 3 ano(s) (180 ECTS) | K9: Presencial | L9: Português | N9: A.M. Lisboa
A10: Atlântica – Instituto Universitário | B10: Portugal | C10: Oeiras | D10: Privada | E10: Licenciatura | F10: Gestão do Transporte Aéreo | G10: Serviços de Transporte | H10: Campus Atlântica, Fábrica da Pólvora de Barcarena | I10: https://www.google.com/search?q=site%3Auatlantica.pt%20Gest%C3%A3o%20do%20Transporte%20A%C3%A9reo%20licenciatura | J10: 3 ano(s) (180 ECTS) | K10: Presencial | L10: Português | N10: A.M. Lisboa
A11: Atlântica – Instituto Universitário | B11: Portugal | C11: Oeiras | D11: Privada | E11: Licenciatura | F11: Gestão em Saúde | G11: Gestão e Administração | H11: Campus Atlântica, Fábrica da Pólvora de Barcarena | I11: https://www.google.com/search?q=site%3Auatlantica.pt%20Gest%C3%A3o%20em%20Sa%C3%BAde%20licenciatura | J11: 3 ano(s) (180 ECTS) | K11: Presencial | L11: Português | N11: A.M. Lisboa
A12: Atlântica – Instituto Universitário | B12: Portugal | C12: Oeiras | D12: Privada | E12: Mestrado | F12: Engenharia de Materiais | G12: Metalurgia e Metalomecânica | H12: Campus Atlântica, Barcarena | I12: https://www.google.com/search?q=site%3Auatlantica.pt%20Engenharia%20de%20Materiais%20mestrado | J12: 2 ano(s) (120 ECTS) | K12: Presencial | L12: Português | N12: A.M. Lisboa
A13: Atlântica – Instituto Universitário | B13: Portugal | C13: Oeiras | D13: Privada | E13: Mestrado | F13: Engenharia e Gestão de Manutenção Aeronáutica | G13: Construção e Reparação de Veículos a Motor | H13: Campus Atlântica, Barcarena | I13: https://www.google.com/search?q=site%3Auatlantica.pt%20Engenharia%20e%20Gest%C3%A3o%20de%20Manuten%C3%A7%C3%A3o%20Aeron%C3%A1utica%20mestrado | J13: 2 ano(s) (120 ECTS) | K13: Presencial | L13: Português | N13: A.M. Lisboa
A14: Atlântica – Instituto Universitário | B14: Portugal | C14: Oeiras | D14: Privada | E14: Mestrado | F14: Engenharia e Gestão de Sistemas de Fabrico | G14: Engenharia e Técnicas Afins | H14: Campus Atlântica, Barcarena | I14: https://www.google.com/search?q=site%3Auatlantica.pt%20Engenharia%20e%20Gest%C3%A3o%20de%20Sistemas%20de%20Fabrico%20mestrado | J14: 2 ano(s) (120 ECTS) | K14: Presencial | L14: Português | M14: Em processo de extinção | N14: A.M. Lisboa
A15: Atlântica – Instituto Universitário | B15: Portugal | C15: Oeiras | D15: Privada | E15: Mestrado | F15: Gestão | G15: Gestão e Administração | H15: Campus Atlântica, Barcarena | I15: https://www.google.com/search?q=site%3Auatlantica.pt%20Gest%C3%A3o%20mestrado | J15: 2 ano(s) (120 ECTS) | K15: Presencial | L15: Português | N15: A.M. Lisboa
A16: Atlântica – Instituto Universitário | B16: Portugal | C16: Oeiras | D16: Privada | E16: Mestrado | F16: Gestão (registo antigo) | G16: Gestão e Administração | H16: Campus Atlântica, Barcarena | I16: https://www.google.com/search?q=site%3Auatlantica.pt%20Gest%C3%A3o%20%28registo%20antigo%29%20mestrado | J16: 2 ano(s) (120 ECTS) | K16: Presencial | L16: Português | M16: Em processo de extinção | N16: A.M. Lisboa
A17: Atlântica – Instituto Universitário | B17: Portugal | C17: Oeiras | D17: Privada | E17: Mestrado | F17: Gestão de Sistemas e Tecnologias de Informação | G17: Ciências Informáticas | H17: Campus Atlântica, Fábrica da Pólvora de Barcarena, 2730‑036 Barcarena | I17: https://www.google.com/search?q=site%3Auatlantica.pt%20Gest%C3%A3o%20de%20Sistemas%20e%20Tecnologias%20de%20Informa%C3%A7%C3%A3o%20mestrado | J17: 2 ano(s) (120 ECTS) | K17: Presencial | L17: Português | N17: A.M. Lisboa
A18: Atlântica – Instituto Universitário | B18: Portugal | C18: Oeiras | D18: Privada | E18: Mestrado | F18: Segurança e Proteção Civil | G18: Proteção de Pessoas e Bens | H18: Campus Atlântica, Barcarena | I18: https://www.google.com/search?q=site%3Auatlantica.pt%20Seguran%C3%A7a%20e%20Prote%C3%A7%C3%A3o%20Civil%20mestrado | J18: 1,5 ano(s) (90 ECTS) | K18: Presencial | L18: Português | N18: A.M. Lisboa
A19: Atlântica – Instituto Universitário | B19: Portugal | C19: Oeiras | D19: Privada | E19: Pós-Graduação | F19: Curso de Especialista Europeu de Adesivos (EAS) | G19: Ciências Dentárias | H19: Atlântica – Instituto Universitário | I19: https://www.google.com/search?q=site%3Auatlantica.pt%20Curso%20de%20Especialista%20Europeu%20de%20Adesivos%20%28EAS%29%20p%C3%B3s-gradua%C3%A7%C3%A3o | J19: Tempo e créditos não indicados nas páginas de lista consultadas | K19: Presencial | L19: Português | N19: A.M. Lisboa
A20: Atlântica – Instituto Universitário | B20: Portugal | C20: Oeiras | D20: Privada | E20: Pós-Graduação | F20: Pós-Graduação de Fitoterapia Clínica | G20: Ciências Farmacêuticas | H20: Atlântica – Instituto Universitário / área de Saúde | I20: https://www.google.com/search?q=site%3Auatlantica.pt%20P%C3%B3s-Gradua%C3%A7%C3%A3o%20de%20Fitoterapia%20Cl%C3%ADnica%20p%C3%B3s-gradua%C3%A7%C3%A3o | J20: Tempo e créditos não indicados na página de lista consultada | K20: Presencial | L20: Português | N20: A.M. Lisboa
A21: Atlântica – Instituto Universitário | B21: Portugal | C21: Oeiras | D21: Privada | E21: Pós-Graduação | F21: Pós-Graduação em Auditoria Hospitalar e Gestão em Saúde | G21: Contabilidade e Fiscalidade | H21: Atlântica – Instituto Universitário / área de Saúde | I21: https://www.google.com/search?q=site%3Auatlantica.pt%20P%C3%B3s-Gradua%C3%A7%C3%A3o%20em%20Auditoria%20Hospitalar%20e%20Gest%C3%A3o%20em%20Sa%C3%BAde%20p%C3%B3s-gradua%C3%A7%C3%A3o | J21: Tempo e créditos não indicados na página de lista consultada | K21: Presencial | L21: Português | N21: A.M. Lisboa
A22: Atlântica – Instituto Universitário | B22: Portugal | C22: Oeiras | D22: Privada | E22: Pós-Graduação | F22: Pós-Graduação em Data Science (PGDS) | G22: Estatística | H22: Atlântica – Instituto Universitário | I22: https://www.google.com/search?q=site%3Auatlantica.pt%20P%C3%B3s-Gradua%C3%A7%C3%A3o%20em%20Data%20Science%20%28PGDS%29%20p%C3%B3s-gradua%C3%A7%C3%A3o | J22: 13 fevereiro a 13 novembro 2025 (≈9 meses); ECTS não indicados | K22: Online | L22: Português | N22: A.M. Lisboa
A23: Atlântica – Instituto Universitário | B23: Portugal | C23: Oeiras | D23: Privada | E23: Pós-Graduação | F23: Pós-Graduação em Gestão da Qualidade e Segurança em Saúde | G23: Enquadramento na Organização | H23: Atlântica – Instituto Universitário / área de Saúde | I23: https://www.google.com/search?q=site%3Auatlantica.pt%20P%C3%B3s-Gradua%C3%A7%C3%A3o%20em%20Gest%C3%A3o%20da%20Qualidade%20e%20Seguran%C3%A7a%20em%20Sa%C3%BAde%20p%C3%B3s-gradua%C3%A7%C3%A3o | J23: Tempo e créditos não indicados na página de lista consultada | K23: Presencial | L23: Português | N23: A.M. Lisboa
A24: Atlântica – Instituto Universitário | B24: Portugal | C24: Oeiras | D24: Privada | E24: Pós-Graduação | F24: Pós-Graduação em Gestão de Companhias Aéreas | G24: Serviços de Transporte | H24: Atlântica – Instituto Universitário (parceria Aeroclass) | I24: https://www.google.com/search?q=site%3Auatlantica.pt%20P%C3%B3s-Gradua%C3%A7%C3%A3o%20em%20Gest%C3%A3o%20de%20Companhias%20A%C3%A9reas%20p%C3%B3s-gradua%C3%A7%C3%A3o | J24: 0,8 ano(s) (45 ECTS) | K24: Online | L24: Português | N24: A.M. Lisboa
A25: Atlântica – Instituto Universitário | B25: Portugal | C25: Oeiras | D25: Privada | E25: Pós-Graduação | F25: Pós-Graduação em Gestão e Liderança dos Serviços de Saúde | G25: Gestão e Administração | H25: Atlântica – Instituto Universitário / ESSATLA | I25: https://www.google.com/search?q=site%3Auatlantica.pt%20P%C3%B3s-Gradua%C3%A7%C3%A3o%20em%20Gest%C3%A3o%20e%20Lideran%C3%A7a%20dos%20Servi%C3%A7os%20de%20Sa%C3%BAde%20p%C3%B3s-gradua%C3%A7%C3%A3o | J25: Tempo e créditos não indicados na página de lista consultada | K25: Presencial | L25: Português | N25: A.M. Lisboa
A26: Atlântica – Instituto Universitário | B26: Portugal | C26: Oeiras | D26: Privada | E26: Pós-Graduação | F26: Pós-Graduação em Materiais Compósitos | G26: Metalurgia e Metalomecânica | H26: Atlântica – Instituto Universitário | I26: https://www.google.com/search?q=site%3Auatlantica.pt%20P%C3%B3s-Gradua%C3%A7%C3%A3o%20em%20Materiais%20Comp%C3%B3sitos%20p%C3%B3s-gradua%C3%A7%C3%A3o | J26: Tempo e créditos não indicados na página de lista consultada | K26: Presencial | L26: Português | N26: A.M. Lisboa
A27: Atlântica – Instituto Universitário | B27: Portugal | C27: Oeiras | D27: Privada | E27: Pós-Graduação | F27: Pós-Graduação em Novos Modelos de Negócio no Mercado Farmacêutico | G27: Ciências Farmacêuticas | H27: Atlântica – Instituto Universitário / área Farmacêutica | I27: https://www.google.com/search?q=site%3Auatlantica.pt%20P%C3%B3s-Gradua%C3%A7%C3%A3o%20em%20Novos%20Modelos%20de%20Neg%C3%B3cio%20no%20Mercado%20Farmac%C3%AAutico%20p%C3%B3s-gradua%C3%A7%C3%A3o | J27: Tempo e créditos não indicados na página de lista consultada | K27: Presencial | L27: Português | N27: A.M. Lisboa
A28: Atlântica – Instituto Universitário | B28: Portugal | C28: Oeiras | D28: Privada | E28: Pós-Graduação | F28: Pós-Graduação em Sistemas Digitais, Inteligência Artificial e Liderança Tecnológica | G28: Ciências Informáticas | H28: Atlântica – Instituto Universitário (parceria Rumos) | I28: https://www.google.com/search?q=site%3Auatlantica.pt%20P%C3%B3s-Gradua%C3%A7%C3%A3o%20em%20Sistemas%20Digitais%2C%20Intelig%C3%AAncia%20Artificial%20e%20Lideran%C3%A7a%20Tecnol%C3%B3gica%20p%C3%B3s-gradua%C3%A7%C3%A3o | J28: ≈ 6 meses; 135 horas; créditos não indicados | K28: Online | L28: Português | N28: A.M. Lisboa
... A50: Escola Superior Artística do Porto | B50: Portugal | C50: Porto | D50: Privada | E50: Licenciatura | F50: Teatro | G50: Música e Artes do Espetáculo | H50: ESAP, Rua dos Navegantes, 51, 4000‑358 Porto | I50: https://www.google.com/search?q=site%3Aesap.pt%20Teatro%20licenciatura | J50: 3 ano(s) (180 ECTS) | K50: Presencial | L50: Português | N50: Norte
A51: Escola Superior Artística do Porto | B51: Portugal | C51: Porto | D51: Privada | E51: Mestrado | F51: Artes Visuais. Práticas Artísticas e Investigação | G51: Belas‑artes | H51: ESAP, Rua dos Navegantes, 51, 4000‑358 Porto | I51: https://www.google.com/search?q=site%3Aesap.pt%20Artes%20Visuais.%20Pr%C3%A1ticas%20Art%C3%ADsticas%20e%20Investiga%C3%A7%C3%A3o%20mestrado | J51: 2 ano(s) (120 ECTS) | K51: Presencial | L51: Português | M51: Em processo de extinção | N51: Norte
A52: Escola Superior Artística do Porto | B52: Portugal | C52: Porto | D52: Privada | E52: Mestrado | F52: Realização – Cinema e Televisão | G52: Audiovisuais e Produção dos Media | H52: ESAP, Rua dos Navegantes, 51, 4000‑358 Porto | I52: https://www.google.com/search?q=site%3Aesap.pt%20Realiza%C3%A7%C3%A3o%20%E2%80%93%20Cinema%20e%20Televis%C3%A3o%20mestrado | J52: 2 ano(s) (120 ECTS) | K52: Presencial | L52: Português | N52: Norte
A53: Escola Superior Artística do Porto | B53: Portugal | C53: Porto | D53: Privada | E53: Mestrado Integrado | F53: Arquitetura | G53: Arquitetura e Urbanismo | H53: ESAP, Rua dos Navegantes, 51, 4000‑358 Porto | I53: https://www.google.com/search?q=site%3Aesap.pt%20Arquitetura%20mestrado%20integrado | J53: 5 ano(s) (300 ECTS) | K53: Presencial | L53: Português | N53: Norte
A54: Escola Superior Artística do Porto | B54: Portugal | C54: Porto | D54: Privada | E54: Pós-Graduação | F54: Argumento para Cinema e Séries de Ficção | G54: Audiovisuais e Produção dos Media | H54: ESAP – Porto | I54: https://www.google.com/search?q=site%3Aesap.pt%20Argumento%20para%20Cinema%20e%20S%C3%A9ries%20de%20Fic%C3%A7%C3%A3o%20p%C3%B3s-gradua%C3%A7%C3%A3o | J54: Não indicado na página pública consultada (tipicamente 1 ano letivo) | K54: Presencial | L54: Português | N54: Norte
A55: Escola Superior Artística do Porto | B55: Portugal | C55: Porto | D55: Privada | E55: Pós-Graduação | F55: Arquitetura Sustentável | G55: Arquitetura e Urbanismo | H55: ESAP – Porto | I55: https://www.google.com/search?q=site%3Aesap.pt%20Arquitetura%20Sustent%C3%A1vel%20p%C3%B3s-gradua%C3%A7%C3%A3o | J55: Não indicado na página pública consultada (tipicamente 1 ano letivo) | K55: Presencial | L55: Português | N55: Norte
A56: Escola Superior Artística do Porto | B56: Portugal | C56: Porto | D56: Privada | E56: Pós-Graduação | F56: Arte Contemporânea | G56: Belas‑artes | H56: ESAP – Porto | I56: https://www.google.com/search?q=site%3Aesap.pt%20Arte%20Contempor%C3%A2nea%20p%C3%B3s-gradua%C3%A7%C3%A3o | J56: Não indicado na página pública consultada (tipicamente 1 ano letivo) | K56: Presencial | L56: Português | N56: Norte
A57: Escola Superior Artística do Porto | B57: Portugal | C57: Porto | D57: Privada | E57: Pós-Graduação | F57: Arte Sonora e Media Arte | G57: Música e Artes do Espetáculo | H57: ESAP – Porto | I57: https://www.google.com/search?q=site%3Aesap.pt%20Arte%20Sonora%20e%20Media%20Arte%20p%C3%B3s-gradua%C3%A7%C3%A3o | J57: Não indicado na página pública consultada (tipicamente 1 ano letivo) | K57: Presencial | L57: Português | N57: Norte
A58: Escola Superior Artística do Porto | B58: Portugal | C58: Porto | D58: Privada | E58: Pós-Graduação | F58: Artes Digitais e Novos Media | G58: Audiovisuais e Produção dos Media | H58: ESAP – Porto | I58: https://www.google.com/search?q=site%3Aesap.pt%20Artes%20Digitais%20e%20Novos%20Media%20p%C3%B3s-gradua%C3%A7%C3%A3o | J58: 1 ano letivo; créditos definidos por regulamento próprio (indicada como especialização/pós‑graduação) | K58: Presencial | L58: Português | N58: Norte
A59: Escola Superior Artística do Porto | B59: Portugal | C59: Porto | D59: Privada | E59: Pós-Graduação | F59: Artes Visuais e Investigação | G59: Belas‑artes | H59: ESAP – Porto | I59: https://www.google.com/search?q=site%3Aesap.pt%20Artes%20Visuais%20e%20Investiga%C3%A7%C3%A3o%20p%C3%B3s-gradua%C3%A7%C3%A3o | J59: Não indicado na página pública consultada (tipicamente 1 ano letivo) | K59: Presencial | L59: Português | N59: Norte
A60: Escola Superior Artística do Porto | B60: Portugal | C60: Porto | D60: Privada | E60: Pós-Graduação | F60: Auto‑edição | G60: Línguas e Literaturas | H60: ESAP – Porto | I60: https://www.google.com/search?q=site%3Aesap.pt%20Auto%E2%80%91edi%C3%A7%C3%A3o%20p%C3%B3s-gradua%C3%A7%C3%A3o | J60: Não indicado na página pública consultada (tipicamente 1 ano letivo) | K60: Presencial | L60: Português | N60: Norte
A61: Escola Superior Artística do Porto | B61: Portugal | C61: Porto | D61: Privada | E61: Pós-Graduação | F61: Banda Desenhada | G61: Design | H61: ESAP – Porto | I61: https://www.google.com/search?q=site%3Aesap.pt%20Banda%20Desenhada%20p%C3%B3s-gradua%C3%A7%C3%A3o | J61: Não indicado na página pública consultada (tipicamente 1 ano letivo) | K61: Presencial | L61: Português | N61: Norte
A62: Escola Superior Artística do Porto | B62: Portugal | C62: Porto | D62: Privada | E62: Pós-Graduação | F62: Curadoria, Cultura Urbana e Práticas Espaciais | G62: História e Arqueologia | H62: ESAP – Porto | I62: https://www.google.com/search?q=site%3Aesap.pt%20Curadoria%2C%20Cultura%20Urbana%20e%20Pr%C3%A1ticas%20Espaciais%20p%C3%B3s-gradua%C3%A7%C3%A3o | J62: 1 ano(s) (60 ECTS) | K62: Presencial | L62: Português | N62: Norte
A63: Escola Superior Artística do Porto | B63: Portugal | C63: Porto | D63: Privada | E63: Pós-Graduação | F63: Direção de Arte | G63: Design | H63: ESAP – Porto | I63: https://www.google.com/search?q=site%3Aesap.pt%20Dire%C3%A7%C3%A3o%20de%20Arte%20p%C3%B3s-gradua%C3%A7%C3%A3o | J63: Não indicado na página pública consultada (tipicamente 1 ano letivo) | K63: Presencial | L63: Português | N63: Norte
... A114: Escola Superior de Educação de Paula Frassinetti | B114: Portugal | C114: Porto | D114: Privada | E114: Licenciatura | F114: Educação Social | G114: Ciências da Educação | H114: Escola Superior de Educação de Paula Frassinetti | I114: https://www.google.com/search?q=site%3Aesepf.pt%20Educa%C3%A7%C3%A3o%20Social%20licenciatura | J114: 3 ano(s) (180 ECTS) | K114: Presencial | L114: Português | N114: Norte
A115: Escola Superior de Educação de Paula Frassinetti | B115: Portugal | C115: Porto | D115: Privada | E115: Mestrado | F115: Ciências da Educação – área de especialização em Educação Especial | G115: Ciências da Educação | H115: Escola Superior de Educação de Paula Frassinetti | I115: https://www.google.com/search?q=site%3Aesepf.pt%20Ci%C3%AAncias%20da%20Educa%C3%A7%C3%A3o%20%E2%80%93%20%C3%A1rea%20de%20especializa%C3%A7%C3%A3o%20em%20Educa%C3%A7%C3%A3o%20Especial%20mestrado | J115: 2 ano(s) (120 ECTS) | K115: Presencial | L115: Português | M115: Em processo de extinção | N115: Norte
A116: Escola Superior de Educação de Paula Frassinetti | B116: Portugal | C116: Porto | D116: Privada | E116: Mestrado | F116: Ciências da Educação – área de especialização em Supervisão Pedagógica | G116: Ciências da Educação | H116: Escola Superior de Educação de Paula Frassinetti | I116: https://www.google.com/search?q=site%3Aesepf.pt%20Ci%C3%AAncias%20da%20Educa%C3%A7%C3%A3o%20%E2%80%93%20%C3%A1rea%20de%20especializa%C3%A7%C3%A3o%20em%20Supervis%C3%A3o%20Pedag%C3%B3gica%20mestrado | J116: 2 ano(s) (120 ECTS) | K116: Presencial | L116: Português | M116: Em processo de extinção | N116: Norte
A117: Escola Superior de Educação de Paula Frassinetti | B117: Portugal | C117: Porto | D117: Privada | E117: Mestrado | F117: Educação | G117: Ciências da Educação | H117: Escola Superior de Educação de Paula Frassinetti | I117: https://www.google.com/search?q=site%3Aesepf.pt%20Educa%C3%A7%C3%A3o%20mestrado | J117: 2 ano(s) (120 ECTS) | K117: Presencial | L117: Português | N117: Norte
A118: Escola Superior de Educação de Paula Frassinetti | B118: Portugal | C118: Porto | D118: Privada | E118: Mestrado | F118: Educação Pré-Escolar | G118: Formação de Professores de Educação de Infância | H118: Escola Superior de Educação de Paula Frassinetti | I118: https://www.google.com/search?q=site%3Aesepf.pt%20Educa%C3%A7%C3%A3o%20Pr%C3%A9-Escolar%20mestrado | J118: 1,5 ano(s) (90 ECTS) | K118: Presencial | L118: Português | N118: Norte
A119: Escola Superior de Educação de Paula Frassinetti | B119: Portugal | C119: Porto | D119: Privada | E119: Mestrado | F119: Educação Pré-Escolar e Ensino do 1.º Ciclo do Ensino Básico | G119: Formação de Professores de Educação de Infância | H119: Escola Superior de Educação de Paula Frassinetti | I119: https://www.google.com/search?q=site%3Aesepf.pt%20Educa%C3%A7%C3%A3o%20Pr%C3%A9-Escolar%20e%20Ensino%20do%201.%C2%BA%20Ciclo%20do%20Ensino%20B%C3%A1sico%20mestrado | J119: 2 ano(s) (120 ECTS) | K119: Presencial | L119: Português | N119: Norte
A120: Escola Superior de Educação de Paula Frassinetti | B120: Portugal | C120: Porto | D120: Privada | E120: Mestrado | F120: Ensino do 1.º Ciclo do Ensino Básico e de Matemática e Ciências Naturais no 2.º Ciclo do Ensino Básico | G120: Formação de Professores do Ensino Básico (1.º e 2.º Ciclos) | H120: Escola Superior de Educação de Paula Frassinetti | I120: https://www.google.com/search?q=site%3Aesepf.pt%20Ensino%20do%201.%C2%BA%20Ciclo%20do%20Ensino%20B%C3%A1sico%20e%20de%20Matem%C3%A1tica%20e%20Ci%C3%AAncias%20Naturais%20no%202.%C2%BA%20Ciclo%20do%20Ensino%20B%C3%A1sico%20mestrado | J120: 2 ano(s) (120 ECTS) | K120: Presencial | L120: Português | N120: Norte
A121: Escola Superior de Educação de Paula Frassinetti | B121: Portugal | C121: Porto | D121: Privada | E121: Mestrado | F121: Ensino do 1.º Ciclo do Ensino Básico e de Português e História e Geografia de Portugal no 2.º Ciclo do Ensino Básico | G121: Formação de Professores do Ensino Básico (1.º e 2.º Ciclos) | H121: Escola Superior de Educação de Paula Frassinetti | I121: https://www.google.com/search?q=site%3Aesepf.pt%20Ensino%20do%201.%C2%BA%20Ciclo%20do%20Ensino%20B%C3%A1sico%20e%20de%20Portugu%C3%AAs%20e%20Hist%C3%B3ria%20e%20Geografia%20de%20Portugal%20no%202.%C2%BA%20Ciclo%20do%20Ensino%20B%C3%A1sico%20mestrado | J121: 2 ano(s) (120 ECTS) | K121: Presencial | L121: Português | N121: Norte
A122: Escola Superior de Educação de Paula Frassinetti | B122: Portugal | C122: Porto | D122: Privada | E122: Mestrado | F122: Intervenção Comunitária | G122: Trabalho Social e Orientação | H122: Escola Superior de Educação de Paula Frassinetti | I122: https://www.google.com/search?q=site%3Aesepf.pt%20Interven%C3%A7%C3%A3o%20Comunit%C3%A1ria%20mestrado | J122: 2 ano(s) (120 ECTS) | K122: Presencial | L122: Português | N122: Norte
A123: Escola Superior de Educação de Paula Frassinetti | B123: Portugal | C123: Porto | D123: Privada | E123: Pós-Graduação | F123: Pós‑Graduação em Inovação e (Trans)Formação Educacional, Pedagogia e Tecnologias Digitais | G123: Ciências da Educação | H123: ESE Paula Frassinetti – Porto | I123: https://www.google.com/search?q=site%3Aesepf.pt%20P%C3%B3s%E2%80%91Gradua%C3%A7%C3%A3o%20em%20Inova%C3%A7%C3%A3o%20e%20%28Trans%29Forma%C3%A7%C3%A3o%20Educacional%2C%20Pedagogia%20e%20Tecnologias%20Digitais%20p%C3%B3s-gradua%C3%A7%C3%A3o | J123: 1 ano(s) (60 ECTS) | K123: Híbrido | L123: Português | N123: Norte
A124: Escola Superior de Educação de Paula Frassinetti | B124: Portugal | C124: Porto | D124: Privada | E124: Pós-Graduação | F124: Pós‑Graduação em Intervenção Psicossocial em Contexto Escolar | G124: Psicologia | H124: ESE Paula Frassinetti | I124: https://www.google.com/search?q=site%3Aesepf.pt%20P%C3%B3s%E2%80%91Gradua%C3%A7%C3%A3o%20em%20Interven%C3%A7%C3%A3o%20Psicossocial%20em%20Contexto%20Escolar%20p%C3%B3s-gradua%C3%A7%C3%A3o | J124: 1 ano; créditos não especificados no excerto (estrutura de pós‑graduação) | K124: Híbrido | L124: Português | N124: Norte
A125: Escola Superior de Educação de Paula Frassinetti | B125: Portugal | C125: Porto | D125: Privada | E125: Pós-Graduação | F125: Pós‑Graduação em Intervenção em Creche: Bem‑estar e Aprendizagem | G125: Ciências da Educação | H125: ESE Paula Frassinetti – Educação de Infância | I125: https://www.google.com/search?q=site%3Aesepf.pt%20P%C3%B3s%E2%80%91Gradua%C3%A7%C3%A3o%20em%20Interven%C3%A7%C3%A3o%20em%20Creche%3A%20Bem%E2%80%91estar%20e%20Aprendizagem%20p%C3%B3s-gradua%C3%A7%C3%A3o | J125: 1 ano; créditos não especificados publicamente (pós‑graduação de curta duração) | K125: Híbrido | L125: Português | N125: Norte
A126: Escola Superior de Enfermagem São Francisco das Misericórdias | B126: Portugal | C126: Lisboa | D126: Privada | E126: Licenciatura | F126: Enfermagem | G126: Enfermagem | H126: Escola Superior de Enfermagem São Francisco das Misericórdias | I126: https://www.google.com/search?q=site%3Aesesfm.pt%20Enfermagem%20licenciatura | J126: 4 ano(s) (240 ECTS) | K126: Presencial | L126: Português | N126: A.M. Lisboa
A127: Escola Superior de Enfermagem São Francisco das Misericórdias | B127: Portugal | C127: Lisboa | D127: Privada | E127: Mestrado | F127: Enfermagem de Reabilitação | G127: Enfermagem | H127: Escola Superior de Enfermagem São Francisco das Misericórdias | I127: https://www.google.com/search?q=site%3Aesesfm.pt%20Enfermagem%20de%20Reabilita%C3%A7%C3%A3o%20mestrado | J127: 1,5 ano(s) (90 ECTS) | K127: Presencial | L127: Português | N127: A.M. Lisboa
A128: Escola Superior de Enfermagem São Francisco das Misericórdias | B128: Portugal | C128: Lisboa | D128: Privada | E128: Mestrado | F128: Enfermagem de Saúde Mental e Psiquiátrica | G128: Enfermagem | H128: Escola Superior de Enfermagem São Francisco das Misericórdias | I128: https://www.google.com/search?q=site%3Aesesfm.pt%20Enfermagem%20de%20Sa%C3%BAde%20Mental%20e%20Psiqui%C3%A1trica%20mestrado | J128: 1,5 ano(s) (90 ECTS) | K128: Presencial | L128: Português | N128: A.M. Lisboa
... A189: Escola Superior de Negócios Atlântico | B189: Portugal | C189: Foz do Douro (Porto) | D189: Privada | E189: Curso Técnico Superior Profissional (CTeSP) | F189: Gestão e Negócios para PME | G189: Gestão e Administração | H189: Escola Superior de Negócios Atlântico | I189: https://www.google.com/search?q=site%3Aesna.pt%20Gest%C3%A3o%20e%20Neg%C3%B3cios%20para%20PME%20CTeSP | J189: 2 ano(s) (120 ECTS) | K189: Presencial | L189: Português | N189: Norte
A190: Escola Superior de Negócios Atlântico | B190: Portugal | C190: Foz do Douro (Porto) | D190: Privada | E190: Licenciatura | F190: Gestão Financeira e Fiscal | G190: Contabilidade e Fiscalidade | H190: Escola Superior de Negócios Atlântico | I190: https://www.google.com/search?q=site%3Aesna.pt%20Gest%C3%A3o%20Financeira%20e%20Fiscal%20licenciatura | J190: 3 ano(s) (180 ECTS) | K190: Presencial | L190: Português | M190: Em processo de extinção | N190: Norte
A191: Escola Superior de Negócios Atlântico | B191: Portugal | C191: Foz do Douro (Porto) | D191: Privada | E191: Licenciatura | F191: Gestão e Negócios | G191: Gestão e Administração | H191: Escola Superior de Negócios Atlântico | I191: https://www.google.com/search?q=site%3Aesna.pt%20Gest%C3%A3o%20e%20Neg%C3%B3cios%20licenciatura | J191: 3 ano(s) (180 ECTS) | K191: Presencial | L191: Português | N191: Norte
A192: Escola Superior de Negócios Atlântico | B192: Portugal | C192: Foz do Douro (Porto) | D192: Privada | E192: Licenciatura | F192: Gestão e Negócios (regime de ensino a distância) | G192: Gestão e Administração | H192: Escola Superior de Negócios Atlântico | I192: https://www.google.com/search?q=site%3Aesna.pt%20Gest%C3%A3o%20e%20Neg%C3%B3cios%20%28regime%20de%20ensino%20a%20dist%C3%A2ncia%29%20licenciatura | J192: 3 ano(s) (180 ECTS) | K192: Online | L192: Português | N192: Norte
A193: Escola Superior de Negócios Atlântico | B193: Portugal | C193: Vila Nova de Gaia / Porto | D193: Privada | E193: Pós-Graduação | F193: Pós‑Graduação em Controlo de Gestão e Finanças | G193: Finanças, Banca e Seguros | H193: Atlântico Business School – Formação Executiva | I193: https://www.google.com/search?q=site%3Aesna.pt%20P%C3%B3s%E2%80%91Gradua%C3%A7%C3%A3o%20em%20Controlo%20de%20Gest%C3%A3o%20e%20Finan%C3%A7as%20p%C3%B3s-gradua%C3%A7%C3%A3o | J193: 0,7 ano(s) (42 ECTS) | K193: Online | L193: Português | N193: Norte
A194: Escola Superior de Negócios Atlântico | B194: Portugal | C194: Porto | D194: Privada | E194: Pós-Graduação Executiva | F194: Pós‑Graduação em Gestão e Negócios – 100% online (MBA Gestão e Negócios) | G194: Gestão e Administração | H194: Atlântico Business School – Ensino a Distância | I194: https://www.google.com/search?q=site%3Aesna.pt%20P%C3%B3s%E2%80%91Gradua%C3%A7%C3%A3o%20em%20Gest%C3%A3o%20e%20Neg%C3%B3cios%20%E2%80%93%20100%25%20online%20%28MBA%20Gest%C3%A3o%20e%20Neg%C3%B3cios%29%20p%C3%B3s-gradua%C3%A7%C3%A3o%20executiva | J194: 2 ano(s) (120 ECTS) | K194: Online | L194: Português | N194: Norte
A195: Escola Superior de Saúde Atlântica | B195: Portugal | C195: Oeiras | D195: Privada | E195: Curso Técnico Superior Profissional (CTeSP) | F195: Gerontologia | G195: Trabalho Social e Orientação | H195: Escola Superior de Saúde Atlântica | I195: https://www.google.com/search?q=site%3Auatlantica.pt%20Gerontologia%20CTeSP | J195: 2 ano(s) (120 ECTS) | K195: Presencial | L195: Português | N195: A.M. Lisboa
A196: Escola Superior de Saúde Atlântica | B196: Portugal | C196: Oeiras | D196: Privada | E196: Curso Técnico Superior Profissional (CTeSP) | F196: Gestão de Serviços de Saúde | G196: Gestão e Administração | H196: Escola Superior de Saúde Atlântica | I196: https://www.google.com/search?q=site%3Auatlantica.pt%20Gest%C3%A3o%20de%20Servi%C3%A7os%20de%20Sa%C3%BAde%20CTeSP | J196: 2 ano(s) (120 ECTS) | K196: Presencial | L196: Português | N196: A.M. Lisboa
A197: Escola Superior de Saúde Atlântica | B197: Portugal | C197: Oeiras | D197: Privada | E197: Curso Técnico Superior Profissional (CTeSP) | F197: Serviço Familiar e Comunitário | G197: Trabalho Social e Orientação | H197: Escola Superior de Saúde Atlântica | I197: https://www.google.com/search?q=site%3Auatlantica.pt%20Servi%C3%A7o%20Familiar%20e%20Comunit%C3%A1rio%20CTeSP | J197: 2 ano(s) (120 ECTS) | K197: Presencial | L197: Português | N197: A.M. Lisboa
A198: Escola Superior de Saúde Atlântica | B198: Portugal | C198: Oeiras | D198: Privada | E198: Licenciatura | F198: Enfermagem | G198: Enfermagem | H198: Escola Superior de Saúde Atlântica | I198: https://www.google.com/search?q=site%3Auatlantica.pt%20Enfermagem%20licenciatura | J198: 4 ano(s) (240 ECTS) | K198: Presencial | L198: Português | N198: A.M. Lisboa
A199: Escola Superior de Saúde Atlântica | B199: Portugal | C199: Oeiras | D199: Privada | E199: Licenciatura | F199: Farmácia | G199: Ciências Farmacêuticas | H199: Escola Superior de Saúde Atlântica | I199: https://www.google.com/search?q=site%3Auatlantica.pt%20Farm%C3%A1cia%20licenciatura | J199: 4 ano(s) (240 ECTS) | K199: Presencial | L199: Português | N199: A.M. Lisboa
A200: Escola Superior de Saúde Atlântica | B200: Portugal | C200: Oeiras | D200: Privada | E200: Licenciatura | F200: Fisioterapia | G200: Terapia e Reabilitação | H200: Escola Superior de Saúde Atlântica | I200: https://www.google.com/search?q=site%3Auatlantica.pt%20Fisioterapia%20licenciatura | J200: 4 ano(s) (240 ECTS) | K200: Presencial | L200: Português | N200: A.M. Lisboa
A201: Escola Superior de Saúde Atlântica | B201: Portugal | C201: Oeiras | D201: Privada | E201: Licenciatura | F201: Osteopatia | G201: Terapia e Reabilitação | H201: Escola Superior de Saúde Atlântica | I201: https://www.google.com/search?q=site%3Auatlantica.pt%20Osteopatia%20licenciatura | J201: 4 ano(s) (240 ECTS) | K201: Presencial | L201: Português | N201: A.M. Lisboa
A202: Escola Superior de Saúde Atlântica | B202: Portugal | C202: Oeiras | D202: Privada | E202: Mestrado | F202: Enfermagem Comunitária na área de Enfermagem de Saúde Comunitária e de Saúde Pública | G202: Enfermagem | H202: Escola Superior de Saúde Atlântica | I202: https://www.google.com/search?q=site%3Auatlantica.pt%20Enfermagem%20Comunit%C3%A1ria%20na%20%C3%A1rea%20de%20Enfermagem%20de%20Sa%C3%BAde%20Comunit%C3%A1ria%20e%20de%20Sa%C3%BAde%20P%C3%BAblica%20mestrado | J202: 1,5 ano(s) (90 ECTS) | K202: Presencial | L202: Português | N202: A.M. Lisboa
... A264: Escola Superior de Saúde Norte da Cruz Vermelha Portuguesa | B264: Portugal | C264: Oliveira de Azeméis | D264: Privada | E264: Curso Técnico Superior Profissional (CTeSP) | F264: Termalismo e Bem-Estar | G264: Terapia e Reabilitação | H264: Escola Superior de Saúde Norte da Cruz Vermelha Portuguesa | I264: https://www.google.com/search?q=site%3Aesscvp.eu%20Termalismo%20e%20Bem-Estar%20CTeSP | J264: 2 ano(s) (120 ECTS) | K264: Presencial | L264: Português | N264: Norte
A265: Escola Superior de Saúde Norte da Cruz Vermelha Portuguesa | B265: Portugal | C265: Oliveira de Azeméis | D265: Privada | E265: Licenciatura | F265: Acupuntura | G265: Terapia e Reabilitação | H265: Escola Superior de Saúde Norte da Cruz Vermelha Portuguesa | I265: https://www.google.com/search?q=site%3Aesscvp.eu%20Acupuntura%20licenciatura | J265: 4 ano(s) (240 ECTS) | K265: Presencial | L265: Português | M265: Em processo de extinção | N265: Norte
A266: Escola Superior de Saúde Norte da Cruz Vermelha Portuguesa | B266: Portugal | C266: Oliveira de Azeméis | D266: Privada | E266: Licenciatura | F266: Enfermagem | G266: Enfermagem | H266: Escola Superior de Saúde Norte da Cruz Vermelha Portuguesa | I266: https://www.google.com/search?q=site%3Aesscvp.eu%20Enfermagem%20licenciatura | J266: 4 ano(s) (240 ECTS) | K266: Presencial | L266: Português | N266: Norte
A267: Escola Superior de Saúde Norte da Cruz Vermelha Portuguesa | B267: Portugal | C267: Oliveira de Azeméis | D267: Privada | E267: Licenciatura | F267: Fisioterapia | G267: Terapia e Reabilitação | H267: Escola Superior de Saúde Norte da Cruz Vermelha Portuguesa | I267: https://www.google.com/search?q=site%3Aesscvp.eu%20Fisioterapia%20licenciatura | J267: 4 ano(s) (240 ECTS) | K267: Presencial | L267: Português | N267: Norte
A268: Escola Superior de Saúde Norte da Cruz Vermelha Portuguesa | B268: Portugal | C268: Oliveira de Azeméis | D268: Privada | E268: Licenciatura | F268: Osteopatia | G268: Terapia e Reabilitação | H268: Escola Superior de Saúde Norte da Cruz Vermelha Portuguesa | I268: https://www.google.com/search?q=site%3Aesscvp.eu%20Osteopatia%20licenciatura | J268: 4 ano(s) (240 ECTS) | K268: Presencial | L268: Português | N268: Norte
A269: Escola Superior de Saúde Norte da Cruz Vermelha Portuguesa | B269: Portugal | C269: Oliveira de Azeméis | D269: Privada | E269: Mestrado | F269: Enfermagem Comunitária na área de Enfermagem de Saúde Familiar | G269: Enfermagem | H269: Escola Superior de Saúde Norte da Cruz Vermelha Portuguesa | I269: https://www.google.com/search?q=site%3Aesscvp.eu%20Enfermagem%20Comunit%C3%A1ria%20na%20%C3%A1rea%20de%20Enfermagem%20de%20Sa%C3%BAde%20Familiar%20mestrado | J269: 1,5 ano(s) (90 ECTS) | K269: Presencial | L269: Português | N269: Norte
A270: Escola Superior de Saúde Norte da Cruz Vermelha Portuguesa | B270: Portugal | C270: Oliveira de Azeméis | D270: Privada | E270: Mestrado | F270: Enfermagem Médico-Cirúrgica | G270: Enfermagem | H270: Escola Superior de Saúde Norte da Cruz Vermelha Portuguesa | I270: https://www.google.com/search?q=site%3Aesscvp.eu%20Enfermagem%20M%C3%A9dico-Cir%C3%BArgica%20mestrado | J270: 1,5 ano(s) (90 ECTS) | K270: Presencial | L270: Português | N270: Norte
A271: Escola Superior de Saúde Norte da Cruz Vermelha Portuguesa | B271: Portugal | C271: Oliveira de Azeméis | D271: Privada | E271: Mestrado | F271: Enfermagem Médico-Cirúrgica na área de Enfermagem à Pessoa em Situação Crónica | G271: Enfermagem | H271: Escola Superior de Saúde Norte da Cruz Vermelha Portuguesa | I271: https://www.google.com/search?q=site%3Aesscvp.eu%20Enfermagem%20M%C3%A9dico-Cir%C3%BArgica%20na%20%C3%A1rea%20de%20Enfermagem%20%C3%A0%20Pessoa%20em%20Situa%C3%A7%C3%A3o%20Cr%C3%B3nica%20mestrado | J271: 1,5 ano(s) (90 ECTS) | K271: Presencial | L271: Português | N271: Norte
A272: Escola Superior de Saúde Norte da Cruz Vermelha Portuguesa | B272: Portugal | C272: Oliveira de Azeméis | D272: Privada | E272: Mestrado | F272: Enfermagem Médico-Cirúrgica na área de Enfermagem à Pessoa em Situação Paliativa | G272: Enfermagem | H272: Escola Superior de Saúde Norte da Cruz Vermelha Portuguesa | I272: https://www.google.com/search?q=site%3Aesscvp.eu%20Enfermagem%20M%C3%A9dico-Cir%C3%BArgica%20na%20%C3%A1rea%20de%20Enfermagem%20%C3%A0%20Pessoa%20em%20Situa%C3%A7%C3%A3o%20Paliativa%20mestrado | J272: 1,5 ano(s) (90 ECTS) | K272: Presencial | L272: Português | N272: Norte
A273: Escola Superior de Saúde Norte da Cruz Vermelha Portuguesa | B273: Portugal | C273: Oliveira de Azeméis | D273: Privada | E273: Mestrado | F273: Enfermagem de Reabilitação | G273: Enfermagem | H273: Escola Superior de Saúde Norte da Cruz Vermelha Portuguesa | I273: https://www.google.com/search?q=site%3Aesscvp.eu%20Enfermagem%20de%20Reabilita%C3%A7%C3%A3o%20mestrado | J273: 1,5 ano(s) (90 ECTS) | K273: Presencial | L273: Português | N273: Norte
A274: Escola Superior de Saúde Norte da Cruz Vermelha Portuguesa | B274: Portugal | C274: Oliveira de Azeméis | D274: Privada | E274: Mestrado | F274: Enfermagem de Saúde Mental e Psiquiátrica | G274: Enfermagem | H274: Escola Superior de Saúde Norte da Cruz Vermelha Portuguesa | I274: https://www.google.com/search?q=site%3Aesscvp.eu%20Enfermagem%20de%20Sa%C3%BAde%20Mental%20e%20Psiqui%C3%A1trica%20mestrado | J274: 1,5 ano(s) (90 ECTS) | K274: Presencial | L274: Português | N274: Norte
A275: Escola Superior de Saúde Norte da Cruz Vermelha Portuguesa | B275: Portugal | C275: Oliveira de Azeméis | D275: Privada | E275: Mestrado | F275: Gestão de Serviços de Saúde | G275: Gestão e Administração | H275: Escola Superior de Saúde Norte da Cruz Vermelha Portuguesa | I275: https://www.google.com/search?q=site%3Aesscvp.eu%20Gest%C3%A3o%20de%20Servi%C3%A7os%20de%20Sa%C3%BAde%20mestrado | J275: 1,5 ano(s) (90 ECTS) | K275: Presencial | L275: Português | N275: Norte
A276: Escola Superior de Saúde Norte da Cruz Vermelha Portuguesa | B276: Portugal | C276: Oliveira de Azeméis / V. N. Famalicão | D276: Privada | E276: Pós-Graduação | F276: Cuidados Intensivos e Emergência | G276: Enfermagem | H276: ESSNorteCVP | I276: https://www.google.com/search?q=site%3Aesscvp.eu%20Cuidados%20Intensivos%20e%20Emerg%C3%AAncia%20p%C3%B3s-gradua%C3%A7%C3%A3o | J276: 0,5 ano(s) (30 ECTS) | K276: Presencial | L276: Português | N276: Norte
A277: Escola Superior de Saúde Norte da Cruz Vermelha Portuguesa | B277: Portugal | C277: Oliveira de Azeméis / V. N. Famalicão | D277: Privada | E277: Pós-Graduação | F277: Emergência Extra‑Hospitalar | G277: Enfermagem | H277: ESSNorteCVP | I277: https://www.google.com/search?q=site%3Aesscvp.eu%20Emerg%C3%AAncia%20Extra%E2%80%91Hospitalar%20p%C3%B3s-gradua%C3%A7%C3%A3o | J277: 0,5 ano(s) (30 ECTS) | K277: Presencial | L277: Português | N277: Norte
... A369: Escola Superior de Saúde do Alcoitão | B369: Portugal | C369: Cascais (Alcoitão) | D369: Privada | E369: Licenciatura | F369: Terapia da Fala | G369: Terapia e Reabilitação | H369: Escola Superior de Saúde do Alcoitão | I369: https://www.google.com/search?q=site%3Aessa.pt%20Terapia%20da%20Fala%20licenciatura | J369: 4 ano(s) (240 ECTS) | K369: Presencial | L369: Português | N369: A.M. Lisboa
A370: Escola Superior de Saúde do Alcoitão | B370: Portugal | C370: Cascais (Alcoitão) | D370: Privada | E370: Mestrado | F370: Abordagens na Criança em Contexto Educativo | G370: Ciências da Educação | H370: Escola Superior de Saúde do Alcoitão | I370: https://www.google.com/search?q=site%3Aessa.pt%20Abordagens%20na%20Crian%C3%A7a%20em%20Contexto%20Educativo%20mestrado | J370: 1,5 ano(s) (90 ECTS) | K370: Presencial | L370: Português | M370: Em processo de extinção | N370: A.M. Lisboa
A371: Escola Superior de Saúde do Alcoitão | B371: Portugal | C371: Cascais (Alcoitão) | D371: Privada | E371: Mestrado | F371: Fisioterapia | G371: Terapia e Reabilitação | H371: Escola Superior de Saúde do Alcoitão | I371: https://www.google.com/search?q=site%3Aessa.pt%20Fisioterapia%20mestrado | J371: 2 ano(s) (120 ECTS) | K371: Presencial | L371: Português | N371: A.M. Lisboa
A372: Escola Superior de Saúde do Alcoitão | B372: Portugal | C372: Cascais (Alcoitão) | D372: Privada | E372: Mestrado | F372: Terapia Ocupacional | G372: Terapia e Reabilitação | H372: Escola Superior de Saúde do Alcoitão | I372: https://www.google.com/search?q=site%3Aessa.pt%20Terapia%20Ocupacional%20mestrado | J372: 2 ano(s) (120 ECTS) | K372: Presencial | L372: Português | N372: A.M. Lisboa
A373: Escola Superior de Saúde do Alcoitão | B373: Portugal | C373: Cascais (Alcoitão) | D373: Privada | E373: Mestrado | F373: Terapia da Fala | G373: Terapia e Reabilitação | H373: Escola Superior de Saúde do Alcoitão | I373: https://www.google.com/search?q=site%3Aessa.pt%20Terapia%20da%20Fala%20mestrado | J373: 1,5 ano(s) (90 ECTS) | K373: Presencial | L373: Português | N373: A.M. Lisboa
A374: Escola Superior de Saúde do Alcoitão | B374: Portugal | C374: Alcabideche | D374: Privada | E374: Pós-Graduação | F374: Nutrição em Contexto e Populações Específicas | G374: Indústrias Alimentares | H374: ESSAlcoitão | I374: https://www.google.com/search?q=site%3Aessa.pt%20Nutri%C3%A7%C3%A3o%20em%20Contexto%20e%20Popula%C3%A7%C3%B5es%20Espec%C3%ADficas%20p%C3%B3s-gradua%C3%A7%C3%A3o | J374: 29 de outubro de 2022 a abril de 2023; ano letivo 2022/2023; PRR 2021/2026 | K374: Online | L374: Português | N374: A.M. Lisboa
A375: Escola Universitária Vasco da Gama | B375: Portugal | C375: Coimbra | D375: Privada | E375: Pós-Graduação | F375: Medicina Felina | G375: Ciências Veterinárias | H375: EUVG | I375: https://www.google.com/search?q=site%3Aeuvg.pt%20Medicina%20Felina%20p%C3%B3s-gradua%C3%A7%C3%A3o | J375: Tempo total não explicitado na página de lista (pós‑graduação em inglês) | K375: Presencial | L375: Português | N375: Centro
A376: Escola Universitária Vasco da Gama | B376: Portugal | C376: Coimbra | D376: Privada | E376: Pós-Graduação | F376: Saúde Pública e One Health | G376: Saúde Pública | H376: EUVG | I376: https://www.google.com/search?q=site%3Aeuvg.pt%20Sa%C3%BAde%20P%C3%BAblica%20e%20One%20Health%20p%C3%B3s-gradua%C3%A7%C3%A3o | J376: Tempo e créditos não indicados na síntese (pós‑graduação avançada) | K376: Presencial | L376: Português | N376: Centro
A377: IPLUSO – Instituto Politécnico da Lusofonia | B377: Portugal | C377: Lisboa | D377: Privada | E377: Pós-Graduação | F377: Automação e Segurança em Sistemas Informáticos | G377: Ciências Informáticas | H377: Escola de Engenharia e Tecnologias (EET) | I377: https://www.google.com/search?q=site%3Aipluso.pt%20Automa%C3%A7%C3%A3o%20e%20Seguran%C3%A7a%20em%20Sistemas%20Inform%C3%A1ticos%20p%C3%B3s-gradua%C3%A7%C3%A3o | J377: 1 ano(s) (60 ECTS) | K377: Híbrido | L377: Português | N377: A.M. Lisboa
A378: IPLUSO – Instituto Politécnico da Lusofonia | B378: Portugal | C378: Lisboa | D378: Privada | E378: Pós-Graduação | F378: Enfermagem Veterinária Clínica | G378: Medicina | H378: Escola Superior de Saúde / área de Veterinária | I378: https://www.google.com/search?q=site%3Aipluso.pt%20Enfermagem%20Veterin%C3%A1ria%20Cl%C3%ADnica%20p%C3%B3s-gradua%C3%A7%C3%A3o | J378: 0,9 ano(s) (54 ECTS) | K378: Híbrido | L378: Português | N378: A.M. Lisboa
A379: IPLUSO – Instituto Politécnico da Lusofonia | B379: Portugal | C379: Lisboa | D379: Privada | E379: Pós-Graduação | F379: Gestão Financeira e Fiscalidade | G379: Contabilidade e Fiscalidade | H379: ECIA / área de Gestão | I379: https://www.google.com/search?q=site%3Aipluso.pt%20Gest%C3%A3o%20Financeira%20e%20Fiscalidade%20p%C3%B3s-gradua%C3%A7%C3%A3o | J379: 1 ano(s) (60 ECTS) | K379: Presencial | L379: Português | N379: A.M. Lisboa
A380: IPLUSO – Instituto Politécnico da Lusofonia | B380: Portugal | C380: Lisboa | D380: Privada | E380: Pós-Graduação | F380: Gestão de Recursos Humanos na área Socioeducativa | G380: Gestão e Administração | H380: ESEL – Escola Superior de Educação da Lusofonia | I380: https://www.google.com/search?q=site%3Aipluso.pt%20Gest%C3%A3o%20de%20Recursos%20Humanos%20na%20%C3%A1rea%20Socioeducativa%20p%C3%B3s-gradua%C3%A7%C3%A3o | J380: 1 ano(s) (60 ECTS) | K380: Presencial | L380: Português | N380: A.M. Lisboa
A381: IPLUSO – Instituto Politécnico da Lusofonia | B381: Portugal | C381: Lisboa | D381: Privada | E381: Pós-Graduação | F381: Instrumentação Cirúrgica | G381: Tecnologias de Diagnóstico e Terapêutica | H381: Escola Superior de Saúde (ESPA/área de saúde) | I381: https://www.google.com/search?q=site%3Aipluso.pt%20Instrumenta%C3%A7%C3%A3o%20Cir%C3%BArgica%20p%C3%B3s-gradua%C3%A7%C3%A3o | J381: 1 ano letivo; 30–36 ECTS (alinhado com PG de Instrumentação em outras escolas) | K381: Presencial | L381: Português | N381: A.M. Lisboa
A382: IPLUSO – Instituto Politécnico da Lusofonia | B382: Portugal | C382: Lisboa | D382: Privada | E382: Pós-Graduação | F382: Mandarim e Cultura Chinesa | G382: Línguas e Literaturas | H382: ESCAD / área de Línguas e Cultura | I382: https://www.google.com/search?q=site%3Aipluso.pt%20Mandarim%20e%20Cultura%20Chinesa%20p%C3%B3s-gradua%C3%A7%C3%A3o | J382: 1 ano(s) (60 ECTS) | K382: Presencial | L382: Português | N382: A.M. Lisboa
... A431: ISCTE – Instituto Universitário de Lisboa | B431: Portugal | C431: Lisboa | D431: Pública | E431: Licenciatura | F431: Finanças e Contabilidade | G431: Finanças, Banca e Seguros | H431: Por confirmar (faculdade/órgão não publicado na fonte oficial) | I431: https://www.google.com/search?q=site%3Aiscte-iul.pt%20Finan%C3%A7as%20e%20Contabilidade%20licenciatura | J431: 3 ano(s) (180 ECTS) | K431: Presencial | L431: Português | N431: A.M. Lisboa
...

Sheet Análise
A1: ANÁLISE — Oferta Formativa de Portugal (tabelas e gráficos por fórmulas COUNTIF)
A3: 1) Cursos por Tipologia
A4: Categoria | B4: Nº cursos
A5: Mestrado | B5: =COUNTIF('Oferta Formativa PT'!E:E,"Mestrado") -> 2126
A6: Licenciatura | B6: =COUNTIF('Oferta Formativa PT'!E:E,"Licenciatura") -> 1498
A7: Pós-Graduação | B7: =COUNTIF('Oferta Formativa PT'!E:E,"Pós-Graduação") -> 1139
A8: Curso Técnico Superior Profissional (CTeSP) | B8: =COUNTIF('Oferta Formativa PT'!E:E,"Curso Técnico Superior Profissional (CTeSP)") -> 893
A9: Mestrado Integrado | B9: =COUNTIF('Oferta Formativa PT'!E:E,"Mestrado Integrado") -> 103
A10: Pós-Graduação Executiva | B10: =COUNTIF('Oferta Formativa PT'!E:E,"Pós-Graduação Executiva") -> 45
A12: 2) Cursos por Modalidade
A13: Categoria | B13: Nº cursos
A14: Presencial | B14: =COUNTIF('Oferta Formativa PT'!K:K,"Presencial") -> 5336
A15: Híbrido / B-learning | B15: =COUNTIF('Oferta Formativa PT'!K:K,"*brido*")+COUNTIF('Oferta Formativa PT'!K:K,"*emipres*") -> 269
A16: Online / A distância | B16: =COUNTIF('Oferta Formativa PT'!K:K,"*nline*")+COUNTIF('Oferta Formativa PT'!K:K,"*dist*") -> 199
A18: 3) Pública vs Privada
A19: Categoria | B19: Nº cursos
A20: Pública | B20: =COUNTIF('Oferta Formativa PT'!D:D,"Pública") -> 4133
A21: Privada | B21: =COUNTIF('Oferta Formativa PT'!D:D,"Privada") -> 1671
A23: 4) Estado
A24: Categoria | B24: Nº cursos
A25: Em funcionamento (ativo) | B25: =COUNTA('Oferta Formativa PT'!A:A)-1-COUNTIF('Oferta Formativa PT'!M:M,"*extin*") -> 5533
A26: Em processo de extinção | B26: =COUNTIF('Oferta Formativa PT'!M:M,"*extin*") -> 271
A28: 5) Cursos por Região
A29: Categoria | B29: Nº cursos
A30: A.M. Lisboa | B30: =COUNTIF('Oferta Formativa PT'!N:N,"A.M. Lisboa") -> 1921
A31: Norte | B31: =COUNTIF('Oferta Formativa PT'!N:N,"Norte") -> 1788
A32: Centro | B32: =COUNTIF('Oferta Formativa PT'!N:N,"Centro") -> 1203
A33: Outras/Múltiplas | B33: =COUNTIF('Oferta Formativa PT'!N:N,"Outras/Múltiplas") -> 411
A34: Alentejo | B34: =COUNTIF('Oferta Formativa PT'!N:N,"Alentejo") -> 244
A35: Algarve | B35: =COUNTIF('Oferta Formativa PT'!N:N,"Algarve") -> 162
A36: Açores | B36: =COUNTIF('Oferta Formativa PT'!N:N,"Açores") -> 58
A37: Madeira | B37: =COUNTIF('Oferta Formativa PT'!N:N,"Madeira") -> 17
A39: 6) Áreas Científicas (Top)
A40: Categoria | B40: Nº cursos
A41: Gestão e Administração | B41: =COUNTIF('Oferta Formativa PT'!G:G,"Gestão e Administração") -> 510
A42: Ciências Informáticas | B42: =COUNTIF('Oferta Formativa PT'!G:G,"Ciências Informáticas") -> 376
A43: Enfermagem | B43: =COUNTIF('Oferta Formativa PT'!G:G,"Enfermagem") -> 261
A44: Ciências da Educação | B44: =COUNTIF('Oferta Formativa PT'!G:G,"Ciências da Educação") -> 211
A45: Biologia e Bioquímica | B45: =COUNTIF('Oferta Formativa PT'!G:G,"Biologia e Bioquímica") -> 186
A46: Marketing e Publicidade | B46: =COUNTIF('Oferta Formativa PT'!G:G,"Marketing e Publicidade") -> 178
A47: Desporto | B47: =COUNTIF('Oferta Formativa PT'!G:G,"Desporto") -> 157
A48: Design | B48: =COUNTIF('Oferta Formativa PT'!G:G,"Design") -> 155
A49: Construção Civil e Engenharia Civil | B49: =COUNTIF('Oferta Formativa PT'!G:G,"Construção Civil e Engenharia Civil") -> 136
A50: Psicologia | B50: =COUNTIF('Oferta Formativa PT'!G:G,"Psicologia") -> 135

Sheet Relatório
A1: RELATÓRIO DA FASE 3
A2: Oferta Formativa do Ensino Superior — Portugal. Levantamento, estruturação, validação e análise da oferta formativa, com base em fontes oficiais. Documento ao serviço da leitura e utilização estratégica desta informação pelo Instituto Piaget.
A4: ════════ I · CONCLUSÕES E RESPOSTA À PROPOSTA FINAL ════════
A5: Pergunta do enunciado:
A6: « Que tendências, concentrações de oferta ou padrões relevantes foram identificados na oferta formativa de Portugal e Espanha, e que utilidade estratégica poderá essa informação ter para análise futura? »
A7: A minha resposta (breve, objetiva e baseada apenas na informação recolhida):
A8: 1) A oferta concentra-se no 2.º ciclo. A tipologia dominante é «Mestrado» (2126 cursos, 37% do total). Somando Mestrado, Mestrado Integrado e as duas Pós-Graduações, o segmento pós-graduado é o maior bloco do mercado português.
A9: 2) Há forte concentração geográfica: a oferta acumula-se na A.M. Lisboa (1921 cursos), no Norte (1788) e no Centro (1203) — estas três regiões concentram a esmagadora maioria da oferta nacional; Alentejo, Algarve, Açores e Madeira têm volumes residuais.
A10: 3) As áreas com mais oferta — e, logo, mais concorrência — são Gestão e Administração (510), Ciências Informáticas (376) e Enfermagem (261), seguidas de Ciências da Educação, Biologia/Bioquímica e Marketing e Publicidade.
A11: 4) Portugal aposta fortemente na formação curta e profissionalizante: o CTeSP (nível 5, 893 cursos) e as Pós-Graduações (1139 + 45 Executivas) somam mais de um terço da oferta — um segmento orientado à empregabilidade e de captação mais rápida.
A12: 5) Predomina o ensino público em volume (4133 cursos públicos vs 1671 privados), mas as instituições privadas e o ensino online/híbrido têm presença relevante, sobretudo na pós-graduação.
A13: Utilidade estratégica para o Instituto Piaget: esta base permite (i) ver onde a concorrência é mais densa, por área e por região, e onde há espaço de oferta; (ii) priorizar prospeção e posicionamento, com destaque para a formação curta (CTeSP e pós-graduação), o segmento mais sensível a marketing de captação; (iii) monitorizar a oferta ativa face à que está em extinção, para antecipar movimentos do mercado.
... A68: Rigor da informação (dados de fontes oficiais, 0 lacunas por inferência, duplicados removidos); uso de fontes oficiais (DGES/A3ES + sites institucionais); organização estruturada (13 colunas + região, sem redundâncias); coerência na classificação (tipologias e áreas uniformizadas); facilidade de leitura e filtragem (AutoFilter por instituição, tipologia, área e região); utilidade prática (KPIs e 6 gráficos na folha «Análise»).
